fsm.v
//------------------------------------------------------------------------
//Finite State Machine
//   
//
//------------------------------------------------------------------------

module fsm
(
input msb_sr,	// most significant bit shift register output
input c_cs,		// conditioned chip select signal put thru input conditioner
input peripheralClkEdge,	// peripheral clockedge of sclk
input clk,					// clk
output MISO_BUFF, 			// miso output enable
output DM_WE,				// Data Memory Write Enable
output ADDR_WE,				// Address Write Enable (for address latch)
output SR_WE				// Shift Register Write Enable
);

    reg [3:0]  counter;
    reg [10:0] LUT_command;
    reg [7:0]  one_hot_signal;
    reg 	   counter_full_holder;
    wire [3:0]  next_index;
    wire  	   Reset_counter;

    initial begin // set start values for one hot state and counter
    	counter <= 4'b0000;
    end

    always @(posedge clk) begin
	    // Post LUT, if reset counter, we reset clock, we start by updating
	    if (Reset_counter) begin
	    	counter <= 4'b0000;
	    end

	    // If we are at the 'done' state, we will go back to the reset state
	    if(next_index == 4'b1000) begin
	    	one_hot_signal = 8'b00000000;
	    end
	    else begin  // if not at done state, we will go to state indicated by next state
	    	one_hot_signal = 1<<next_index; 
	    end

    	// update LUT command signal based upon inputs
    	LUT_command[10] = c_cs;
    	LUT_command[9] = msb_sr;
    	LUT_command[7:0] = one_hot_signal;

    	// if peripheralclkedge, we update the counter and see if its at 8 or not
	    if (peripheralClkEdge) begin
	    	counter <= counter + 4'b0001; 	// add 1 to the counter
	    	if (counter > 4'b0111) begin
	    		LUT_command[8] = 1;			// raise flag in command if counter is full
	    	end
	    	else begin
	    		LUT_command[8] = 0;			// don't raise flag if counter is not full
	    	end
	    end
    end
    fsm_LUT	fms_lut(SR_WE, Reset_counter, DM_WE, ADDR_WE, MISO_BUFF, next_index, LUT_command);

endmodule


// Table Abbreviations
// Key:
//      First bit is Cs, 2nd is msb, 3rd is counterfull
//		Last 8 are next state index (Which state the name lines up to) in one hot form

`define RESET_1   11'b11000000000 // initial state with msb 1
`define RESET_2   11'b10000000000 // initial state with msb 0
`define RESET_3   11'b110xxxxxxxx // initial state with msb 1
`define RESET_4   11'b100xxxxxxxx // initial state with msb 0

`define Get_1     11'b10000000001 // Get state with msb 0, counter_full 0
`define Get_2     11'b11000000001 // Get state with msb 1, counter_full 0
`define Get_3     11'b10100000001 // Get state with msb 0, counter_full 1
`define Get_4     11'b11100000001 // Get state with msb 1, counter_full 1

`define Got_1     11'b11100000010 // Got state with msb 1, counter_full 1, goes to read
`define Got_2     11'b10100000010 // Got state with msb 0, counter_full 1, goes to write

`define Read1     11'b11000000100 // Read 1 state with msb 1, countefull 0

`define Read2     11'b11000001000 // Read 2 state with msb 1, counterfull 0

`define Read3_1   11'b10000010000 // Read 3 state with msb 0, counter_full 0
`define Read3_2   11'b11000010000 // Read 3 state with msb 1, counter_full 0
`define Read3_3   11'b10100010000 // Read 3 state with msb 0, counter_full 1
`define Read3_4   11'b11100010000 // Read 3 state with msb 1, counter_full 1

`define Write1_1  11'b10000100000 // Write 1 state with msb 0, counter_full 0
`define Write1_2  11'b11000100000 // Write 1 state with msb 1, counter_full 0
`define Write1_3  11'b10100100000 // Write 1 state with msb 0, counter_full 1
`define Write1_4  11'b11100100000 // Write 1 state with msb 1, counter_full 1

`define Write2_1  11'b10101000000 // Write 2 state with msb 0, counter_full 1
`define Write2_2  11'b11101000000 // Write 2 state with msb 1, counter_full 1

`define Done_1    11'b10110000000 // Done satate with msb 0, counter_full 1
`define Done_2    11'b11110000000 // Done satate with msb 1, counter_full 1


module fsm_LUT // Converts the commands to a more convenient format
(
    output reg  SR_WE,
    output reg  Reset_counter,
    output reg  DM_WE,
    output reg  ADDR_WE,
    output reg  MISO_BUFF,
    output reg [3:0]  next_index,
    input[10:0]  LUT_command
);

    always @(LUT_command) begin
      case (LUT_command)
      	
      	`RESET_1:    begin SR_WE = 0; Reset_counter=1; DM_WE = 0; ADDR_WE = 0; MISO_BUFF = 0; next_index = 4'b0000; end
      	`RESET_2:    begin SR_WE = 0; Reset_counter=1; DM_WE = 0; ADDR_WE = 0; MISO_BUFF = 0; next_index = 4'b0000; end
 		`RESET_3:    begin SR_WE = 0; Reset_counter=1; DM_WE = 0; ADDR_WE = 0; MISO_BUFF = 0; next_index = 4'b0000; end
      	`RESET_4:    begin SR_WE = 0; Reset_counter=1; DM_WE = 0; ADDR_WE = 0; MISO_BUFF = 0; next_index = 4'b0000; end

        `Get_1:  	begin SR_WE = 0; Reset_counter=0; DM_WE = 0; ADDR_WE = 0; MISO_BUFF = 0; next_index = 4'b0000; end
		`Get_2:  	begin SR_WE = 0; Reset_counter=0; DM_WE = 0; ADDR_WE = 0; MISO_BUFF = 0; next_index = 4'b0000; end
        `Get_3:  	begin SR_WE = 0; Reset_counter=0; DM_WE = 0; ADDR_WE = 0; MISO_BUFF = 0; next_index = 4'b0001; end
        `Get_4:  	begin SR_WE = 0; Reset_counter=0; DM_WE = 0; ADDR_WE = 0; MISO_BUFF = 0; next_index = 4'b0001; end

        `Got_1:  	begin SR_WE = 0; Reset_counter=1; DM_WE = 0; ADDR_WE = 1; MISO_BUFF = 0; next_index = 4'b0010; end
        `Got_2:  	begin SR_WE = 0; Reset_counter=1; DM_WE = 0; ADDR_WE = 1; MISO_BUFF = 0; next_index = 4'b0101; end

        `Read1:  	begin SR_WE = 0; Reset_counter=0; DM_WE = 0; ADDR_WE = 0; MISO_BUFF = 0; next_index = 4'b0011; end
        
        `Read2: 	begin SR_WE = 1; Reset_counter=0; DM_WE = 0; ADDR_WE = 0; MISO_BUFF = 0; next_index = 4'b0100; end
        
        `Read3_1:  	begin SR_WE = 0; Reset_counter=0; DM_WE = 0; ADDR_WE = 0; MISO_BUFF = 1; next_index = 4'b0100; end
        `Read3_2:  	begin SR_WE = 0; Reset_counter=0; DM_WE = 0; ADDR_WE = 0; MISO_BUFF = 1; next_index = 4'b0100; end
        `Read3_3:  	begin SR_WE = 0; Reset_counter=0; DM_WE = 0; ADDR_WE = 0; MISO_BUFF = 1; next_index = 4'b0111; end
        `Read3_4:  	begin SR_WE = 0; Reset_counter=0; DM_WE = 0; ADDR_WE = 0; MISO_BUFF = 1; next_index = 4'b0111; end
        
 
        `Write1_1:  begin SR_WE = 0; Reset_counter=0; DM_WE = 1; ADDR_WE = 0; MISO_BUFF = 0; next_index = 4'b0101; end
        `Write1_2:  begin SR_WE = 0; Reset_counter=0; DM_WE = 1; ADDR_WE = 0; MISO_BUFF = 0; next_index = 4'b0101; end
        `Write1_3:  begin SR_WE = 0; Reset_counter=0; DM_WE = 1; ADDR_WE = 0; MISO_BUFF = 0; next_index = 4'b0110; end
        `Write1_4:  begin SR_WE = 0; Reset_counter=0; DM_WE = 1; ADDR_WE = 0; MISO_BUFF = 0; next_index = 4'b0110; end

        
        `Write2_1:  begin SR_WE = 0; Reset_counter=0; DM_WE = 0; ADDR_WE = 0; MISO_BUFF = 0; next_index = 4'b0111; end
        `Write2_1:  begin SR_WE = 0; Reset_counter=0; DM_WE = 0; ADDR_WE = 0; MISO_BUFF = 0; next_index = 4'b0111; end

        `Done_1:  	begin SR_WE = 0; Reset_counter=1; DM_WE = 0; ADDR_WE = 0; MISO_BUFF = 0; next_index = 4'b1000; end
        `Done_2:  	begin SR_WE = 0; Reset_counter=1; DM_WE = 0; ADDR_WE = 0; MISO_BUFF = 0; next_index = 4'b1000; end
      endcase
    end
endmodule

fsm.t.v
//------------------------------------------------------------------------
// Shift Register test bench
//------------------------------------------------------------------------
`timescale 1ns / 1ps

`include "fsm.v"

module testfsm();

    reg msb_sr;   // most significant bit shift register output
    reg c_cs;     // conditioned chip select signal put thru input conditioner
    reg peripheralClkEdge;    // peripheral clockedge of sclk
    reg clk;                  // clk
    wire MISO_BUFF;           // miso output enable
    wire DM_WE;               // Data Memory Write Enable
    wire ADDR_WE;             // Address Write Enable (for address latch)
    wire SR_WE;                // Shift Register Write Enable

    // Instantiate with parameter width = 8
    fsm dut(.clk(clk), 
    		           .peripheralClkEdge(peripheralClkEdge),
    		           .msb_sr(msb_sr), 
    		           .c_cs(c_cs), 
    		           .MISO_BUFF(MISO_BUFF), 
    		           .DM_WE(DM_WE),
                       .ADDR_WE(ADDR_WE),
    		           .SR_WE(SR_WE));
    always begin
    #1 clk = ~clk;
    //#4 peripheralClkEdge= ~peripheralClkEdge;
    end

    initial begin
    	// Your Test Code
        $dumpfile("fsm.vcd");
        $dumpvars();

        $display(" clk  |   pclk   |  pload |     pin      |  sin  |      pout     |  sout  |  expected");
        
        // Initial Conditions time = 0
        clk=1; peripheralClkEdge = 0; msb_sr = 0; c_cs = 1; #2
        // Now we will assign values for different test cases
        peripheralClkEdge = 1; msb_sr = 0; c_cs =1; #1
        peripheralClkEdge = 0; msb_sr = 0; c_cs =1; #3
        peripheralClkEdge = 1; msb_sr = 0; c_cs =1; #1
        peripheralClkEdge = 0; msb_sr = 0; c_cs =1; #3
        peripheralClkEdge = 1; msb_sr = 0; c_cs =1; #1
        peripheralClkEdge = 0; msb_sr = 0; c_cs =1; #3
        peripheralClkEdge = 1; msb_sr = 0; c_cs =1; #1
        peripheralClkEdge = 0; msb_sr = 0; c_cs =1; #3
        peripheralClkEdge = 1; msb_sr = 0; c_cs =1; #1
        peripheralClkEdge = 0; msb_sr = 0; c_cs =1; #3
        peripheralClkEdge = 1; msb_sr = 0; c_cs =1; #1
        peripheralClkEdge = 0; msb_sr = 0; c_cs =1; #3
        peripheralClkEdge = 1; msb_sr = 0; c_cs =1; #1
        peripheralClkEdge = 0; msb_sr = 0; c_cs =1; #3
        peripheralClkEdge = 1; msb_sr = 0; c_cs =1; #1
        peripheralClkEdge = 0; msb_sr = 0; c_cs =1; #3
        peripheralClkEdge = 1; msb_sr = 0; c_cs =1; #1
        peripheralClkEdge = 0; msb_sr = 0; c_cs =1; #3
        peripheralClkEdge = 1; msb_sr = 0; c_cs =1; #1
        peripheralClkEdge = 0; msb_sr = 0; c_cs =1; #3
        peripheralClkEdge = 1; msb_sr = 0; c_cs =1; #1
        peripheralClkEdge = 0; msb_sr = 0; c_cs =1; #3
        peripheralClkEdge = 1; msb_sr = 0; c_cs =1; #1
        peripheralClkEdge = 0; msb_sr = 0; c_cs =1; #3
        #10 $finish;
    end

endmodule

fsm.vcd
$date
	Tue Oct 25 01:53:08 2016
$end
$version
	Icarus Verilog
$end
$timescale
	1ps
$end
$scope module testfsm $end
$var wire 1 ! ADDR_WE $end
$var wire 1 " DM_WE $end
$var wire 1 # MISO_BUFF $end
$var wire 1 $ SR_WE $end
$var reg 1 % c_cs $end
$var reg 1 & clk $end
$var reg 1 ' msb_sr $end
$var reg 1 ( peripheralClkEdge $end
$scope module dut $end
$var wire 1 ! ADDR_WE $end
$var wire 1 " DM_WE $end
$var wire 1 # MISO_BUFF $end
$var wire 1 ) Reset_counter $end
$var wire 1 $ SR_WE $end
$var wire 1 * c_cs $end
$var wire 1 + clk $end
$var wire 1 , msb_sr $end
$var wire 4 - next_index [3:0] $end
$var wire 1 . peripheralClkEdge $end
$var reg 11 / LUT_command [10:0] $end
$var reg 4 0 counter [3:0] $end
$var reg 8 1 one_hot_signal [7:0] $end
$scope module fms_lut $end
$var wire 11 2 LUT_command [10:0] $end
$var reg 1 3 ADDR_WE $end
$var reg 1 4 DM_WE $end
$var reg 1 5 MISO_BUFF $end
$var reg 1 6 Reset_counter $end
$var reg 1 7 SR_WE $end
$var reg 4 8 next_index [3:0] $end
$upscope $end
$upscope $end
$upscope $end
$enddefinitions $end
#0
$dumpvars
bx 8
x7
x6
x5
x4
x3
b10xxxxxxxxx 2
bx 1
b0 0
b10xxxxxxxxx /
0.
bx -
0,
1+
1*
x)
0(
0'
1&
1%
x$
x#
x"
x!
$end
#1000
0&
0+
#2000
b1 0
b0 8
b0 -
05
0#
03
0!
04
0"
16
1)
07
0$
b100xxxxxxxx 2
b100xxxxxxxx /
1&
1+
1(
1.
#3000
0&
0+
0(
0.
#4000
b0 0
06
0)
b10000000001 2
b10000000001 /
b1 1
1&
1+
#5000
0&
0+
#6000
b1 0
b10000000001 /
1&
1+
1(
1.
#7000
0&
0+
0(
0.
#8000
b10000000001 /
1&
1+
#9000
0&
0+
#10000
b10 0
b10000000001 /
1&
1+
1(
1.
#11000
0&
0+
0(
0.
#12000
b10000000001 /
1&
1+
#13000
0&
0+
#14000
b11 0
b10000000001 /
1&
1+
1(
1.
#15000
0&
0+
0(
0.
#16000
b10000000001 /
1&
1+
#17000
0&
0+
#18000
b100 0
b10000000001 /
1&
1+
1(
1.
#19000
0&
0+
0(
0.
#20000
b10000000001 /
1&
1+
#21000
0&
0+
#22000
b101 0
b10000000001 /
1&
1+
1(
1.
#23000
0&
0+
0(
0.
#24000
b10000000001 /
1&
1+
#25000
0&
0+
#26000
b110 0
b10000000001 /
1&
1+
1(
1.
#27000
0&
0+
0(
0.
#28000
b10000000001 /
1&
1+
#29000
0&
0+
#30000
b111 0
b10000000001 /
1&
1+
1(
1.
#31000
0&
0+
0(
0.
#32000
b10000000001 /
1&
1+
#33000
0&
0+
#34000
b1000 0
b10000000001 /
1&
1+
1(
1.
#35000
0&
0+
0(
0.
#36000
b10000000001 /
1&
1+
#37000
0&
0+
#38000
b1001 0
b1 8
b1 -
b10100000001 2
b10100000001 /
1&
1+
1(
1.
#39000
0&
0+
0(
0.
#40000
b101 8
b101 -
13
1!
16
1)
b10100000010 2
b10100000010 /
b10 1
1&
1+
#41000
0&
0+
#42000
b1010 0
b110 8
b110 -
03
0!
14
1"
06
0)
b10100100000 2
b10100100000 /
b100000 1
1&
1+
1(
1.
#43000
0&
0+
0(
0.
#44000
b111 8
b111 -
04
0"
b10101000000 2
b10101000000 /
b1000000 1
1&
1+
#45000
0&
0+
#46000
b1011 0
b1000 8
b1000 -
16
1)
b10110000000 2
b10110000000 /
b10000000 1
1&
1+
1(
1.
#47000
0&
0+
0(
0.
#48000
b0 0
b10100000000 2
b10100000000 /
b0 1
1&
1+
#49000
0&
0+
#50000
b10100000000 /
1&
1+
#51000
0&
0+
#52000
b10100000000 /
1&
1+
#53000
0&
0+
#54000
b10100000000 /
1&
1+
#55000
0&
0+
#56000
b10100000000 /
1&
1+
#57000
0&
0+
#58000
b10100000000 /
1&
1+
#59000
0&
0+
#60000
b10100000000 /
1&
1+
