fsm.v
//------------------------------------------------------------------------
//Finite State Machine
//   
//
//------------------------------------------------------------------------

module fsm
(
input msb_sr,	// most significant bit shift register output
input c_cs,		// conditioned chip select signal put thru input conditioner
input peripheralClkEdge,	// peripheral clockedge of sclk
input clk,					// clk
output MISO_BUFF, 			// miso output enable
output DM_WE,				// Data Memory Write Enable
output ADDR_WE,				// Address Write Enable (for address latch)
output SR_WE				// Shift Register Write Enable
);

    reg [3:0]  counter;
    reg [10:0] LUT_command;
    reg [7:0]  one_hot_signal;
    reg 	   counter_full_holder;
    wire [3:0]  next_index_wire;
    reg [3:0]  next_index_reg;
    wire  	   Reset_counter;
    reg 		c_cs_reg;

    initial begin // set start values for one hot state and counter
    	counter <= 4'b0000;
    	next_index_reg <= 4'b0000;
    	one_hot_signal <= 8'b00000000;
    end

    always @(posedge clk) begin

    	if (c_cs_reg == c_cs && c_cs == 0) begin
			next_index_reg = next_index_wire;
    	end

	    // Post LUT, if reset counter, we reset clock, we start by updating
	    if (Reset_counter) begin
	    	counter <= 4'b0000;
	    	counter_full_holder <= 0;
	    	LUT_command[8] <= 0;
	    end
	    else if (peripheralClkEdge) begin
	    	counter <= counter + 4'b0001; 	// add 1 to the counter
	    	if (counter == 4'b0111) begin
	    		LUT_command[8] = 1;			// raise flag in command if counter is full
	    		counter_full_holder =1;

	    	end
	    	else begin
	    		LUT_command[8] = 0;			// don't raise flag if counter is not full
	    		counter_full_holder = 0;
	    	end
	    end

	    if (c_cs == 1) begin
	    	one_hot_signal = 8'b00000000;
	    end
	    else begin  // if not at done state, we will go to state indicated by next state
	    	one_hot_signal = 1<<next_index_reg; 
	    end

    	// update LUT command signal based upon inputs
    	LUT_command[10] = c_cs;
    	LUT_command[9] = msb_sr;
    	LUT_command[7:0] = one_hot_signal;

    c_cs_reg <= c_cs;

    end
    fsm_LUT	fms_lut(SR_WE, Reset_counter, DM_WE, ADDR_WE, MISO_BUFF, next_index_wire, LUT_command);

endmodule


// Table Abbreviations
// Key:
//      First bit is Cs, 2nd is msb, 3rd is counterfull
//		Last 8 are next state index (Which state the name lines up to) in one hot form	

`define RESET_1   11'b01000000000 // initial state with msb 1
`define RESET_2   11'b00000000000 // initial state with msb 0
`define RESET_3   11'b010xxxxxxxx // initial state with msb 1
`define RESET_4   11'b000xxxxxxxx // initial state with msb 0
`define RESET_5   11'b11000000000 // initial state with msb 1 cs off
`define RESET_6   11'b10000000000 // initial state with msb 0 cs off
`define RESET_7   11'b110xxxxxxxx // initial state with msb 1 cs off
`define RESET_8   11'b100xxxxxxxx // initial state with msb 0 cs off

`define Get_1     11'b00000000001 // Get state with msb 0, counter_full 0
`define Get_2     11'b01000000001 // Get state with msb 1, counter_full 0
`define Get_3     11'b00100000001 // Get state with msb 0, counter_full 1
`define Get_4     11'b01100000001 // Get state with msb 1, counter_full 1

`define Got_1     11'b01100000010 // Got state with msb 1, counter_full 1, goes to read
`define Got_2     11'b00100000010 // Got state with msb 0, counter_full 1, goes to write

`define Read1     11'b01000000100 // Read 1 state with msb 1, countefull 0

`define Read2     11'b01000001000 // Read 2 state with msb 1, counterfull 0

`define Read3_1   11'b00000010000 // Read 3 state with msb 0, counter_full 0
`define Read3_2   11'b01000010000 // Read 3 state with msb 1, counter_full 0
`define Read3_3   11'b00100010000 // Read 3 state with msb 0, counter_full 1
`define Read3_4   11'b01100010000 // Read 3 state with msb 1, counter_full 1

`define Write1_1  11'b00000100000 // Write 1 state with msb 0, counter_full 0
`define Write1_2  11'b01000100000 // Write 1 state with msb 1, counter_full 0
`define Write1_3  11'b00100100000 // Write 1 state with msb 0, counter_full 1
`define Write1_4  11'b01100100000 // Write 1 state with msb 1, counter_full 1

`define Write2_1  11'b00101000000 // Write 2 state with msb 0, counter_full 1
`define Write2_2  11'b01101000000 // Write 2 state with msb 1, counter_full 1

`define Done_1    11'b00110000000 // Done satate with msb 0, counter_full 1
`define Done_2    11'b01110000000 // Done satate with msb 1, counter_full 1


module fsm_LUT // Converts the commands to a more convenient format
(
    output reg  SR_WE,
    output reg  Reset_counter,
    output reg  DM_WE,
    output reg  ADDR_WE,
    output reg  MISO_BUFF,
    output reg [3:0]  next_index,
    input[10:0]  LUT_command
);

    always @(LUT_command) begin
      case (LUT_command)
      	
      	`RESET_1:    begin SR_WE = 0; Reset_counter=1; DM_WE = 0; ADDR_WE = 0; MISO_BUFF = 0; next_index = 4'b0000; end
      	`RESET_2:    begin SR_WE = 0; Reset_counter=1; DM_WE = 0; ADDR_WE = 0; MISO_BUFF = 0; next_index = 4'b0000; end
 		`RESET_3:    begin SR_WE = 0; Reset_counter=1; DM_WE = 0; ADDR_WE = 0; MISO_BUFF = 0; next_index = 4'b0000; end
      	`RESET_4:    begin SR_WE = 0; Reset_counter=1; DM_WE = 0; ADDR_WE = 0; MISO_BUFF = 0; next_index = 4'b0000; end
      	`RESET_5:    begin SR_WE = 0; Reset_counter=1; DM_WE = 0; ADDR_WE = 0; MISO_BUFF = 0; next_index = 4'b0000; end
      	`RESET_6:    begin SR_WE = 0; Reset_counter=1; DM_WE = 0; ADDR_WE = 0; MISO_BUFF = 0; next_index = 4'b0000; end
 		`RESET_7:    begin SR_WE = 0; Reset_counter=1; DM_WE = 0; ADDR_WE = 0; MISO_BUFF = 0; next_index = 4'b0000; end
      	`RESET_8:    begin SR_WE = 0; Reset_counter=1; DM_WE = 0; ADDR_WE = 0; MISO_BUFF = 0; next_index = 4'b0000; end

        `Get_1:  	begin SR_WE = 0; Reset_counter=0; DM_WE = 0; ADDR_WE = 0; MISO_BUFF = 0; next_index = 4'b0000; end
		`Get_2:  	begin SR_WE = 0; Reset_counter=0; DM_WE = 0; ADDR_WE = 0; MISO_BUFF = 0; next_index = 4'b0000; end
        `Get_3:  	begin SR_WE = 0; Reset_counter=0; DM_WE = 0; ADDR_WE = 0; MISO_BUFF = 0; next_index = 4'b0001; end
        `Get_4:  	begin SR_WE = 0; Reset_counter=0; DM_WE = 0; ADDR_WE = 0; MISO_BUFF = 0; next_index = 4'b0001; end

        `Got_1:  	begin SR_WE = 0; Reset_counter=1; DM_WE = 0; ADDR_WE = 1; MISO_BUFF = 0; next_index = 4'b0010; end
        `Got_2:  	begin SR_WE = 0; Reset_counter=1; DM_WE = 0; ADDR_WE = 1; MISO_BUFF = 0; next_index = 4'b0101; end

        `Read1:  	begin SR_WE = 0; Reset_counter=0; DM_WE = 0; ADDR_WE = 0; MISO_BUFF = 0; next_index = 4'b0011; end
        
        `Read2: 	begin SR_WE = 1; Reset_counter=0; DM_WE = 0; ADDR_WE = 0; MISO_BUFF = 0; next_index = 4'b0100; end
        
        `Read3_1:  	begin SR_WE = 0; Reset_counter=0; DM_WE = 0; ADDR_WE = 0; MISO_BUFF = 1; next_index = 4'b0100; end
        `Read3_2:  	begin SR_WE = 0; Reset_counter=0; DM_WE = 0; ADDR_WE = 0; MISO_BUFF = 1; next_index = 4'b0100; end
        `Read3_3:  	begin SR_WE = 0; Reset_counter=0; DM_WE = 0; ADDR_WE = 0; MISO_BUFF = 1; next_index = 4'b0111; end
        `Read3_4:  	begin SR_WE = 0; Reset_counter=0; DM_WE = 0; ADDR_WE = 0; MISO_BUFF = 1; next_index = 4'b0111; end
        
 
        `Write1_1:  begin SR_WE = 0; Reset_counter=0; DM_WE = 0; ADDR_WE = 0; MISO_BUFF = 0; next_index = 4'b0101; end
        `Write1_2:  begin SR_WE = 0; Reset_counter=0; DM_WE = 0; ADDR_WE = 0; MISO_BUFF = 0; next_index = 4'b0101; end
        `Write1_3:  begin SR_WE = 0; Reset_counter=0; DM_WE = 0; ADDR_WE = 0; MISO_BUFF = 0; next_index = 4'b0110; end
        `Write1_4:  begin SR_WE = 0; Reset_counter=0; DM_WE = 0; ADDR_WE = 0; MISO_BUFF = 0; next_index = 4'b0110; end

        
        `Write2_1:  begin SR_WE = 0; Reset_counter=0; DM_WE = 1; ADDR_WE = 0; MISO_BUFF = 0; next_index = 4'b0111; end
        `Write2_1:  begin SR_WE = 0; Reset_counter=0; DM_WE = 1; ADDR_WE = 0; MISO_BUFF = 0; next_index = 4'b0111; end

        `Done_1:  	begin SR_WE = 0; Reset_counter=1; DM_WE = 0; ADDR_WE = 0; MISO_BUFF = 0; next_index = 4'b0000; end
        `Done_2:  	begin SR_WE = 0; Reset_counter=1; DM_WE = 0; ADDR_WE = 0; MISO_BUFF = 0; next_index = 4'b0000; end
      endcase
    end
endmodule

fsm.t.v
//------------------------------------------------------------------------
// Shift Register test bench
//------------------------------------------------------------------------
`timescale 1ns / 1ps

`include "fsm.v"

module testfsm();

    reg msb_sr;   // most significant bit shift register output
    reg c_cs;     // conditioned chip select signal put thru input conditioner
    reg peripheralClkEdge;    // peripheral clockedge of sclk
    reg clk;                  // clk
    wire MISO_BUFF;           // miso output enable
    wire DM_WE;               // Data Memory Write Enable
    wire ADDR_WE;             // Address Write Enable (for address latch)
    wire SR_WE;                // Shift Register Write Enable

    // Instantiate with parameter width = 8
    fsm dut(.clk(clk), 
    		           .peripheralClkEdge(peripheralClkEdge),
    		           .msb_sr(msb_sr), 
    		           .c_cs(c_cs), 
    		           .MISO_BUFF(MISO_BUFF), 
    		           .DM_WE(DM_WE),
                       .ADDR_WE(ADDR_WE),
    		           .SR_WE(SR_WE));
    always begin
    #1 clk = ~clk;
    //#4 peripheralClkEdge= ~peripheralClkEdge;
    end

    initial begin
    	// Your Test Code
        $dumpfile("fsm.vcd");
        $dumpvars();

        $display(" clk  |   pclk   |  pload |     pin      |  sin  |      pout     |  sout  |  expected");
        
        // Initial Conditions time = 0
        clk=1; peripheralClkEdge = 0; msb_sr = 0; c_cs = 1; #5

        // Testing Write
        peripheralClkEdge = 1; msb_sr = 0; c_cs =0; #2
        peripheralClkEdge = 0; msb_sr = 0; c_cs =0; #5
        peripheralClkEdge = 1; msb_sr = 0; c_cs =0; #2
        peripheralClkEdge = 0; msb_sr = 0; c_cs =0; #5
        peripheralClkEdge = 1; msb_sr = 0; c_cs =0; #2
        peripheralClkEdge = 0; msb_sr = 0; c_cs =0; #5
        peripheralClkEdge = 1; msb_sr = 0; c_cs =0; #2
        peripheralClkEdge = 0; msb_sr = 0; c_cs =0; #5
        peripheralClkEdge = 1; msb_sr = 0; c_cs =0; #2
        peripheralClkEdge = 0; msb_sr = 0; c_cs =0; #5
        peripheralClkEdge = 1; msb_sr = 0; c_cs =0; #2
        peripheralClkEdge = 0; msb_sr = 0; c_cs =0; #5
        peripheralClkEdge = 1; msb_sr = 0; c_cs =0; #2
        peripheralClkEdge = 0; msb_sr = 0; c_cs =0; #5
        peripheralClkEdge = 1; msb_sr = 0; c_cs =0; #2
        peripheralClkEdge = 0; msb_sr = 0; c_cs =0; #5
        peripheralClkEdge = 1; msb_sr = 0; c_cs =0; #2
        peripheralClkEdge = 0; msb_sr = 0; c_cs =0; #5
        peripheralClkEdge = 1; msb_sr = 0; c_cs =0; #2
        peripheralClkEdge = 0; msb_sr = 0; c_cs =0; #5
        peripheralClkEdge = 1; msb_sr = 0; c_cs =0; #2
        peripheralClkEdge = 0; msb_sr = 0; c_cs =0; #5
        peripheralClkEdge = 1; msb_sr = 0; c_cs =0; #2
        peripheralClkEdge = 0; msb_sr = 0; c_cs =0; #5
        peripheralClkEdge = 1; msb_sr = 0; c_cs =0; #2
        peripheralClkEdge = 0; msb_sr = 0; c_cs =0; #5
        peripheralClkEdge = 1; msb_sr = 0; c_cs =0; #2
        peripheralClkEdge = 0; msb_sr = 0; c_cs =0; #5
        peripheralClkEdge = 1; msb_sr = 0; c_cs =0; #2
        peripheralClkEdge = 0; msb_sr = 0; c_cs =0; #5
        peripheralClkEdge = 1; msb_sr = 0; c_cs =0; #2
        peripheralClkEdge = 0; msb_sr = 0; c_cs =0; #5
        peripheralClkEdge = 1; msb_sr = 0; c_cs =0; #2
        peripheralClkEdge = 0; msb_sr = 0; c_cs =0; #5


        // Testing Write
        peripheralClkEdge = 1; msb_sr = 1; c_cs =0; #2
        peripheralClkEdge = 0; msb_sr = 1; c_cs =0; #5
        peripheralClkEdge = 1; msb_sr = 1; c_cs =0; #2
        peripheralClkEdge = 0; msb_sr = 1; c_cs =0; #5
        peripheralClkEdge = 1; msb_sr = 1; c_cs =0; #2
        peripheralClkEdge = 0; msb_sr = 1; c_cs =0; #5
        peripheralClkEdge = 1; msb_sr = 1; c_cs =0; #2
        peripheralClkEdge = 0; msb_sr = 1; c_cs =0; #5
        peripheralClkEdge = 1; msb_sr = 1; c_cs =0; #2
        peripheralClkEdge = 0; msb_sr = 1; c_cs =0; #5
        peripheralClkEdge = 1; msb_sr = 1; c_cs =0; #2
        peripheralClkEdge = 0; msb_sr = 1; c_cs =0; #5
        peripheralClkEdge = 1; msb_sr = 1; c_cs =0; #2
        peripheralClkEdge = 0; msb_sr = 1; c_cs =0; #5
        peripheralClkEdge = 1; msb_sr = 1; c_cs =0; #2
        peripheralClkEdge = 0; msb_sr = 1; c_cs =0; #5
        peripheralClkEdge = 1; msb_sr = 1; c_cs =0; #2
        peripheralClkEdge = 0; msb_sr = 1; c_cs =0; #5
        peripheralClkEdge = 1; msb_sr = 1; c_cs =0; #2
        peripheralClkEdge = 0; msb_sr = 1; c_cs =0; #5
        peripheralClkEdge = 1; msb_sr = 1; c_cs =0; #2
        peripheralClkEdge = 0; msb_sr = 1; c_cs =0; #5
        peripheralClkEdge = 1; msb_sr = 1; c_cs =0; #2
        peripheralClkEdge = 0; msb_sr = 1; c_cs =0; #5
        peripheralClkEdge = 1; msb_sr = 1; c_cs =0; #2
        peripheralClkEdge = 0; msb_sr = 1; c_cs =0; #5
        peripheralClkEdge = 1; msb_sr = 1; c_cs =0; #2
        peripheralClkEdge = 0; msb_sr = 1; c_cs =0; #5
        peripheralClkEdge = 1; msb_sr = 1; c_cs =0; #2
        peripheralClkEdge = 0; msb_sr = 1; c_cs =0; #5
        peripheralClkEdge = 1; msb_sr = 1; c_cs =0; #2
        peripheralClkEdge = 0; msb_sr = 1; c_cs =0; #5
        peripheralClkEdge = 1; msb_sr = 1; c_cs =0; #2
        peripheralClkEdge = 0; msb_sr = 1; c_cs =0; #5


        // Testing cs off
        peripheralClkEdge = 1; msb_sr = 1; c_cs =1; #2
        peripheralClkEdge = 0; msb_sr = 1; c_cs =1; #5
        peripheralClkEdge = 1; msb_sr = 1; c_cs =1; #2
        peripheralClkEdge = 0; msb_sr = 1; c_cs =1; #5
        peripheralClkEdge = 1; msb_sr = 1; c_cs =1; #2
        peripheralClkEdge = 0; msb_sr = 1; c_cs =1; #5
        peripheralClkEdge = 1; msb_sr = 1; c_cs =1; #2
        peripheralClkEdge = 0; msb_sr = 1; c_cs =1; #5
        peripheralClkEdge = 1; msb_sr = 1; c_cs =1; #2
        peripheralClkEdge = 0; msb_sr = 1; c_cs =1; #5
        peripheralClkEdge = 1; msb_sr = 1; c_cs =1; #2
        peripheralClkEdge = 0; msb_sr = 1; c_cs =1; #5
        peripheralClkEdge = 1; msb_sr = 1; c_cs =1; #2
        peripheralClkEdge = 0; msb_sr = 1; c_cs =1; #5
        peripheralClkEdge = 1; msb_sr = 1; c_cs =1; #2
        peripheralClkEdge = 0; msb_sr = 1; c_cs =1; #5
        peripheralClkEdge = 1; msb_sr = 1; c_cs =1; #2
        peripheralClkEdge = 0; msb_sr = 1; c_cs =1; #5
        peripheralClkEdge = 1; msb_sr = 1; c_cs =1; #2
        peripheralClkEdge = 0; msb_sr = 1; c_cs =1; #5
        peripheralClkEdge = 1; msb_sr = 1; c_cs =1; #2
        peripheralClkEdge = 0; msb_sr = 1; c_cs =1; #5
        peripheralClkEdge = 1; msb_sr = 1; c_cs =1; #2
        peripheralClkEdge = 0; msb_sr = 1; c_cs =1; #5
        peripheralClkEdge = 1; msb_sr = 1; c_cs =1; #2
        peripheralClkEdge = 0; msb_sr = 1; c_cs =1; #5
        peripheralClkEdge = 1; msb_sr = 1; c_cs =1; #2
        peripheralClkEdge = 0; msb_sr = 1; c_cs =1; #5
        peripheralClkEdge = 1; msb_sr = 1; c_cs =1; #2
        peripheralClkEdge = 0; msb_sr = 1; c_cs =1; #5
        peripheralClkEdge = 1; msb_sr = 1; c_cs =1; #2
        peripheralClkEdge = 0; msb_sr = 1; c_cs =1; #5

        // Testing Write
        peripheralClkEdge = 1; msb_sr = 1; c_cs =0; #2
        peripheralClkEdge = 0; msb_sr = 1; c_cs =0; #5
        peripheralClkEdge = 1; msb_sr = 1; c_cs =0; #2
        peripheralClkEdge = 0; msb_sr = 1; c_cs =0; #5
        peripheralClkEdge = 1; msb_sr = 1; c_cs =0; #2
        peripheralClkEdge = 0; msb_sr = 1; c_cs =0; #5
        peripheralClkEdge = 1; msb_sr = 1; c_cs =0; #2
        peripheralClkEdge = 0; msb_sr = 1; c_cs =0; #5
        peripheralClkEdge = 1; msb_sr = 1; c_cs =0; #2
        peripheralClkEdge = 0; msb_sr = 1; c_cs =0; #5
        peripheralClkEdge = 1; msb_sr = 1; c_cs =0; #2
        peripheralClkEdge = 0; msb_sr = 1; c_cs =0; #5
        peripheralClkEdge = 1; msb_sr = 1; c_cs =0; #2
        peripheralClkEdge = 0; msb_sr = 1; c_cs =0; #5
        peripheralClkEdge = 1; msb_sr = 1; c_cs =0; #2
        peripheralClkEdge = 0; msb_sr = 1; c_cs =0; #5
        peripheralClkEdge = 1; msb_sr = 1; c_cs =0; #2
        peripheralClkEdge = 0; msb_sr = 1; c_cs =0; #5
        peripheralClkEdge = 1; msb_sr = 1; c_cs =0; #2
        peripheralClkEdge = 0; msb_sr = 1; c_cs =0; #5
        peripheralClkEdge = 1; msb_sr = 1; c_cs =0; #2
        peripheralClkEdge = 0; msb_sr = 1; c_cs =0; #5
        peripheralClkEdge = 1; msb_sr = 1; c_cs =0; #2
        peripheralClkEdge = 0; msb_sr = 1; c_cs =0; #5
    
      
        #10 $finish;
    end

endmodule

fsm.vcd
$date
	Tue Oct 25 04:23:49 2016
$end
$version
	Icarus Verilog
$end
$timescale
	1ps
$end
$scope module testfsm $end
$var wire 1 ! ADDR_WE $end
$var wire 1 " DM_WE $end
$var wire 1 # MISO_BUFF $end
$var wire 1 $ SR_WE $end
$var reg 1 % c_cs $end
$var reg 1 & clk $end
$var reg 1 ' msb_sr $end
$var reg 1 ( peripheralClkEdge $end
$scope module dut $end
$var wire 1 ! ADDR_WE $end
$var wire 1 " DM_WE $end
$var wire 1 # MISO_BUFF $end
$var wire 1 ) Reset_counter $end
$var wire 1 $ SR_WE $end
$var wire 1 * c_cs $end
$var wire 1 + clk $end
$var wire 1 , msb_sr $end
$var wire 4 - next_index_wire [3:0] $end
$var wire 1 . peripheralClkEdge $end
$var reg 11 / LUT_command [10:0] $end
$var reg 1 0 c_cs_reg $end
$var reg 4 1 counter [3:0] $end
$var reg 1 2 counter_full_holder $end
$var reg 4 3 next_index_reg [3:0] $end
$var reg 8 4 one_hot_signal [7:0] $end
$scope module fms_lut $end
$var wire 11 5 LUT_command [10:0] $end
$var reg 1 6 ADDR_WE $end
$var reg 1 7 DM_WE $end
$var reg 1 8 MISO_BUFF $end
$var reg 1 9 Reset_counter $end
$var reg 1 : SR_WE $end
$var reg 4 ; next_index [3:0] $end
$upscope $end
$upscope $end
$upscope $end
$enddefinitions $end
#0
$dumpvars
bx ;
x:
x9
x8
x7
x6
b10x00000000 5
b0 4
b0 3
x2
b0 1
10
b10x00000000 /
0.
bx -
0,
1+
1*
x)
0(
0'
1&
1%
x$
x#
x"
x!
$end
#1000
0&
0+
#2000
b10x00000000 /
1&
1+
#3000
0&
0+
#4000
b10x00000000 /
1&
1+
#5000
0&
0+
0%
0*
1(
1.
#6000
00
b1 1
b0 ;
b0 -
08
0#
06
0!
07
0"
09
0)
0:
0$
b1 4
02
b1 /
b1 5
1&
1+
#7000
0&
0+
0(
0.
#8000
b1 /
1&
1+
#9000
0&
0+
#10000
b1 /
1&
1+
#11000
0&
0+
#12000
b10 1
b1 /
1&
1+
1(
1.
#13000
0&
0+
#14000
b1 /
1&
1+
0(
0.
#15000
0&
0+
#16000
b1 /
1&
1+
#17000
0&
0+
#18000
b1 /
1&
1+
#19000
0&
0+
1(
1.
#20000
b11 1
b1 /
1&
1+
#21000
0&
0+
0(
0.
#22000
b1 /
1&
1+
#23000
0&
0+
#24000
b1 /
1&
1+
#25000
0&
0+
#26000
b100 1
b1 /
1&
1+
1(
1.
#27000
0&
0+
#28000
b1 /
1&
1+
0(
0.
#29000
0&
0+
#30000
b1 /
1&
1+
#31000
0&
0+
#32000
b1 /
1&
1+
#33000
0&
0+
1(
1.
#34000
b101 1
b1 /
1&
1+
#35000
0&
0+
0(
0.
#36000
b1 /
1&
1+
#37000
0&
0+
#38000
b1 /
1&
1+
#39000
0&
0+
#40000
b110 1
b1 /
1&
1+
1(
1.
#41000
0&
0+
#42000
b1 /
1&
1+
0(
0.
#43000
0&
0+
#44000
b1 /
1&
1+
#45000
0&
0+
#46000
b1 /
1&
1+
#47000
0&
0+
1(
1.
#48000
b111 1
b1 /
1&
1+
#49000
0&
0+
0(
0.
#50000
b1 /
1&
1+
#51000
0&
0+
#52000
b1 /
1&
1+
#53000
0&
0+
#54000
b1000 1
b1 ;
b1 -
12
b100000001 /
b100000001 5
1&
1+
1(
1.
#55000
0&
0+
#56000
b101 ;
b101 -
16
1!
19
1)
b100000010 5
b100000010 /
b10 4
b1 3
1&
1+
0(
0.
#57000
0&
0+
#58000
02
b0 1
b101 ;
b101 -
06
0!
09
0)
b100000 5
b100000 /
b100000 4
b101 3
1&
1+
#59000
0&
0+
#60000
b100000 /
1&
1+
#61000
0&
0+
1(
1.
#62000
b1 1
b100000 /
1&
1+
#63000
0&
0+
0(
0.
#64000
b100000 /
1&
1+
#65000
0&
0+
#66000
b100000 /
1&
1+
#67000
0&
0+
#68000
b10 1
b100000 /
1&
1+
1(
1.
#69000
0&
0+
#70000
b100000 /
1&
1+
0(
0.
#71000
0&
0+
#72000
b100000 /
1&
1+
#73000
0&
0+
#74000
b100000 /
1&
1+
#75000
0&
0+
1(
1.
#76000
b11 1
b100000 /
1&
1+
#77000
0&
0+
0(
0.
#78000
b100000 /
1&
1+
#79000
0&
0+
#80000
b100000 /
1&
1+
#81000
0&
0+
#82000
b100 1
b100000 /
1&
1+
1(
1.
#83000
0&
0+
#84000
b100000 /
1&
1+
0(
0.
#85000
0&
0+
#86000
b100000 /
1&
1+
#87000
0&
0+
#88000
b100000 /
1&
1+
#89000
0&
0+
1(
1.
#90000
b101 1
b100000 /
1&
1+
#91000
0&
0+
0(
0.
#92000
b100000 /
1&
1+
#93000
0&
0+
#94000
b100000 /
1&
1+
#95000
0&
0+
#96000
b110 1
b100000 /
1&
1+
1(
1.
#97000
0&
0+
#98000
b100000 /
1&
1+
0(
0.
#99000
0&
0+
#100000
b100000 /
1&
1+
#101000
0&
0+
#102000
b100000 /
1&
1+
#103000
0&
0+
1(
1.
#104000
b111 1
b100000 /
1&
1+
#105000
0&
0+
0(
0.
#106000
b100000 /
1&
1+
#107000
0&
0+
#108000
b100000 /
1&
1+
#109000
0&
0+
#110000
b1000 1
b110 ;
b110 -
12
b100100000 /
b100100000 5
1&
1+
1(
1.
#111000
0&
0+
#112000
b111 ;
b111 -
17
1"
b101000000 5
b101000000 /
b1000000 4
b110 3
1&
1+
0(
0.
#113000
0&
0+
#114000
b0 ;
b0 -
07
0"
19
1)
b110000000 5
b110000000 /
b10000000 4
b111 3
1&
1+
#115000
0&
0+
#116000
02
b0 1
b0 ;
b0 -
09
0)
b1 5
b1 /
b1 4
b0 3
1&
1+
#117000
0&
0+
1(
1.
#118000
b1 1
b1 /
1&
1+
#119000
0&
0+
0(
0.
#120000
b1 /
1&
1+
#121000
0&
0+
#122000
b1 /
1&
1+
#123000
0&
0+
#124000
b10 1
b1000000001 5
b1000000001 /
1&
1+
1'
1,
1(
1.
#125000
0&
0+
#126000
b1000000001 /
1&
1+
0(
0.
#127000
0&
0+
#128000
b1000000001 /
1&
1+
#129000
0&
0+
#130000
b1000000001 /
1&
1+
#131000
0&
0+
1(
1.
#132000
b11 1
b1000000001 /
1&
1+
#133000
0&
0+
0(
0.
#134000
b1000000001 /
1&
1+
#135000
0&
0+
#136000
b1000000001 /
1&
1+
#137000
0&
0+
#138000
b100 1
b1000000001 /
1&
1+
1(
1.
#139000
0&
0+
#140000
b1000000001 /
1&
1+
0(
0.
#141000
0&
0+
#142000
b1000000001 /
1&
1+
#143000
0&
0+
#144000
b1000000001 /
1&
1+
#145000
0&
0+
1(
1.
#146000
b101 1
b1000000001 /
1&
1+
#147000
0&
0+
0(
0.
#148000
b1000000001 /
1&
1+
#149000
0&
0+
#150000
b1000000001 /
1&
1+
#151000
0&
0+
#152000
b110 1
b1000000001 /
1&
1+
1(
1.
#153000
0&
0+
#154000
b1000000001 /
1&
1+
0(
0.
#155000
0&
0+
#156000
b1000000001 /
1&
1+
#157000
0&
0+
#158000
b1000000001 /
1&
1+
#159000
0&
0+
1(
1.
#160000
b111 1
b1000000001 /
1&
1+
#161000
0&
0+
0(
0.
#162000
b1000000001 /
1&
1+
#163000
0&
0+
#164000
b1000000001 /
1&
1+
#165000
0&
0+
#166000
b1000 1
b1 ;
b1 -
12
b1100000001 /
b1100000001 5
1&
1+
1(
1.
#167000
0&
0+
#168000
b10 ;
b10 -
16
1!
19
1)
b1100000010 5
b1100000010 /
b10 4
b1 3
1&
1+
0(
0.
#169000
0&
0+
#170000
b11 ;
b11 -
06
0!
09
0)
02
b0 1
b1000000100 5
b1000000100 /
b100 4
b10 3
1&
1+
#171000
0&
0+
#172000
b100 ;
b100 -
1:
1$
b1000001000 5
b1000001000 /
b1000 4
b11 3
1&
1+
#173000
0&
0+
1(
1.
#174000
b1 1
18
1#
0:
0$
b1000010000 5
b10000 4
b1000010000 /
b100 3
1&
1+
#175000
0&
0+
0(
0.
#176000
b1000010000 /
1&
1+
#177000
0&
0+
#178000
b1000010000 /
1&
1+
#179000
0&
0+
#180000
b10 1
b1000010000 /
1&
1+
1(
1.
#181000
0&
0+
#182000
b1000010000 /
1&
1+
0(
0.
#183000
0&
0+
#184000
b1000010000 /
1&
1+
#185000
0&
0+
#186000
b1000010000 /
1&
1+
#187000
0&
0+
1(
1.
#188000
b11 1
b1000010000 /
1&
1+
#189000
0&
0+
0(
0.
#190000
b1000010000 /
1&
1+
#191000
0&
0+
#192000
b1000010000 /
1&
1+
#193000
0&
0+
#194000
b100 1
b1000010000 /
1&
1+
1(
1.
#195000
0&
0+
#196000
b1000010000 /
1&
1+
0(
0.
#197000
0&
0+
#198000
b1000010000 /
1&
1+
#199000
0&
0+
#200000
b1000010000 /
1&
1+
#201000
0&
0+
1(
1.
#202000
b101 1
b1000010000 /
1&
1+
#203000
0&
0+
0(
0.
#204000
b1000010000 /
1&
1+
#205000
0&
0+
#206000
b1000010000 /
1&
1+
#207000
0&
0+
#208000
b110 1
b1000010000 /
1&
1+
1(
1.
#209000
0&
0+
#210000
b1000010000 /
1&
1+
0(
0.
#211000
0&
0+
#212000
b1000010000 /
1&
1+
#213000
0&
0+
#214000
b1000010000 /
1&
1+
#215000
0&
0+
1(
1.
#216000
b111 1
b1000010000 /
1&
1+
#217000
0&
0+
0(
0.
#218000
b1000010000 /
1&
1+
#219000
0&
0+
#220000
b1000010000 /
1&
1+
#221000
0&
0+
#222000
b1000 1
b111 ;
b111 -
12
b1100010000 /
b1100010000 5
1&
1+
1(
1.
#223000
0&
0+
#224000
b0 ;
b0 -
08
0#
19
1)
b1110000000 5
b1110000000 /
b10000000 4
b111 3
1&
1+
0(
0.
#225000
0&
0+
#226000
02
b0 1
b0 ;
b0 -
09
0)
b1000000001 5
b1000000001 /
b1 4
b0 3
1&
1+
#227000
0&
0+
#228000
b1000000001 /
1&
1+
#229000
0&
0+
1(
1.
#230000
b1 1
b1000000001 /
1&
1+
#231000
0&
0+
0(
0.
#232000
b1000000001 /
1&
1+
#233000
0&
0+
#234000
b1000000001 /
1&
1+
#235000
0&
0+
#236000
b10 1
b1000000001 /
1&
1+
1(
1.
#237000
0&
0+
#238000
b1000000001 /
1&
1+
0(
0.
#239000
0&
0+
#240000
b1000000001 /
1&
1+
#241000
0&
0+
#242000
b1000000001 /
1&
1+
#243000
0&
0+
1%
1*
1(
1.
#244000
10
b11 1
19
1)
b11000000000 5
b0 4
b11000000000 /
1&
1+
#245000
0&
0+
0(
0.
#246000
b0 1
b11000000000 /
1&
1+
#247000
0&
0+
#248000
b11000000000 /
1&
1+
#249000
0&
0+
#250000
b11000000000 /
1&
1+
1(
1.
#251000
0&
0+
#252000
b11000000000 /
1&
1+
0(
0.
#253000
0&
0+
#254000
b11000000000 /
1&
1+
#255000
0&
0+
#256000
b11000000000 /
1&
1+
#257000
0&
0+
1(
1.
#258000
b11000000000 /
1&
1+
#259000
0&
0+
0(
0.
#260000
b11000000000 /
1&
1+
#261000
0&
0+
#262000
b11000000000 /
1&
1+
#263000
0&
0+
#264000
b11000000000 /
1&
1+
1(
1.
#265000
0&
0+
#266000
b11000000000 /
1&
1+
0(
0.
#267000
0&
0+
#268000
b11000000000 /
1&
1+
#269000
0&
0+
#270000
b11000000000 /
1&
1+
#271000
0&
0+
1(
1.
#272000
b11000000000 /
1&
1+
#273000
0&
0+
0(
0.
#274000
b11000000000 /
1&
1+
#275000
0&
0+
#276000
b11000000000 /
1&
1+
#277000
0&
0+
#278000
b11000000000 /
1&
1+
1(
1.
#279000
0&
0+
#280000
b11000000000 /
1&
1+
0(
0.
#281000
0&
0+
#282000
b11000000000 /
1&
1+
#283000
0&
0+
#284000
b11000000000 /
1&
1+
#285000
0&
0+
1(
1.
#286000
b11000000000 /
1&
1+
#287000
0&
0+
0(
0.
