fsm_pk.v
module fsm
(
input clk,
input msb_sr,	// most significant bit shift register output
input c_cs,		// conditioned chip select signal put thru input conditioner
input peripheralClkEdge,	// peripheral clockedge of sclk
output reg MISO_BUFF, 			// miso output enable
output reg DM_WE,				// Data Memory Write Enable
output reg ADDR_WE,				// Address Write Enable (for address latch)
output reg SR_WE				// Shift Register Write Enable
);
reg[7:0] state;

localparam GET = 8'b00000001,
		   GOT = 8'b00000010,
		   READ1 = 8'b00000100,
		   READ2 = 8'b00001000,
		   READ3 = 8'b00010000,
		   WRITE1 = 8'b00100000,
		   WRITE2 = 8'b01000000,
		   DONE = 8'b10000000;
reg [3:0] counter;
reg counter_reset;
reg reset_flg;

initial begin
counter = 4'b0000;
counter_reset = 0;
//reset_flg = 0;
end



always @(posedge clk) begin

	//if (counter_reset) begin
	//counter_reset <= 0;
	//counter = 4'b0000;
	//reset_flg <= 1;
	//end

	

	if (peripheralClkEdge && !counter_reset) begin
		counter <= counter + 1;
	end 

	if(counter_reset || c_cs ) begin
		counter <=0;
		counter_reset <= 0;
	end

	if (c_cs) begin
		state <= GET;
		counter <= 4'b0000;
		MISO_BUFF <= 0;
		DM_WE <=0;
		ADDR_WE <=0;
		SR_WE <=0;
	end

	else begin
		case (state)
			GET: begin
				if (counter==4'b1000) begin
					state <= GOT;
				end
				else begin
					state <= GET;
					//counter <= counter + 4'b0001;
				end
			end

			GOT: begin
				if (msb_sr ) begin	// && reset_flg
					state <= READ1;
					//reset_flg <=0;
				end
				else begin
					if (!msb_sr ) begin // && reset_flg
						state <= WRITE1;
						// reset_flg <=0;
					end
				end
			end

			READ1: begin
				state <= READ2;
			end

			READ2: begin
				// reset_flg <= 0;
				state <= READ3;
			end

			READ3: begin
				if (counter == 4'b1000) begin
					state <= DONE;
				end
				else begin
					state <= READ3;
					//counter <= counter + 1;
				end
			end

			WRITE1: begin
				if (counter == 4'b1000) begin
					state <= WRITE2;
					// counter_reset <= 1;
				end
				else begin
					// counter_reset <=0;
					state <= WRITE1;
					//counter <= counter + 1;
				end
			end

			WRITE2: begin
				state <= DONE;
			end

			DONE: begin
				// if (reset_flg); begin
					state <= GET;
					// reset_flg <=0;
				// end
			end
		endcase
//end // @ peripheralclkedge
end
end
always @(state) begin
	case (state)
		GET: begin
			MISO_BUFF <= 0;
			DM_WE <=0;
			ADDR_WE <=0;
			SR_WE <=0;
		end

		GOT: begin
			MISO_BUFF <= 0;
			ADDR_WE <= 1;
			DM_WE <=0;
			SR_WE <=0;
			counter_reset <= 1;
			counter <= 4'b0000;
		end

		READ1: begin
			MISO_BUFF <= 0;
			DM_WE <=0;
			ADDR_WE <=0;
			SR_WE <=0;
		end

		READ2: begin
			MISO_BUFF <= 0;
			DM_WE <=0;
			ADDR_WE <=0;
			SR_WE <=1;
		end

		READ3: begin
			MISO_BUFF <=1;
			DM_WE <=0;
			ADDR_WE <=0;
			SR_WE <=0;
		end

		WRITE1: begin
			MISO_BUFF <= 0;
			DM_WE <=0;
			ADDR_WE <=0;
			SR_WE <=0;
		end

		WRITE2: begin
			MISO_BUFF <= 0;
			DM_WE <=1;
			ADDR_WE <=0;
			SR_WE <=0;
		end

		DONE: begin
			MISO_BUFF <= 0;
			DM_WE <=0;
			ADDR_WE <=0;
			SR_WE <=0;
			counter <= 4'b0000;
		end
	endcase
end // @ state

endmodule

fsm.t.v
//------------------------------------------------------------------------
// Shift Register test bench
//------------------------------------------------------------------------
`timescale 1ns / 1ps

`include "fsm_pk.v"

module testfsm();

    reg msb_sr;   // most significant bit shift register output
    reg c_cs;     // conditioned chip select signal put thru input conditioner
    reg peripheralClkEdge;    // peripheral clockedge of sclk
    reg clk;                  // clk
    wire MISO_BUFF;           // miso output enable
    wire DM_WE;               // Data Memory Write Enable
    wire ADDR_WE;             // Address Write Enable (for address latch)
    wire SR_WE;                // Shift Register Write Enable

    // Instantiate with parameter width = 8
    fsm dut(.clk(clk), 
    		           .peripheralClkEdge(peripheralClkEdge),
    		           .msb_sr(msb_sr), 
    		           .c_cs(c_cs), 
    		           .MISO_BUFF(MISO_BUFF), 
    		           .DM_WE(DM_WE),
                       .ADDR_WE(ADDR_WE),
    		           .SR_WE(SR_WE));
    always begin
    #1 clk = ~clk;
    //#4 peripheralClkEdge= ~peripheralClkEdge;
    end

    initial begin
    	// Your Test Code
        $dumpfile("fsm.vcd");
        $dumpvars();

        $display(" clk  |   pclk   |  pload |     pin      |  sin  |      pout     |  sout  |  expected");
        
        // Initial Conditions time = 0
        clk=1; peripheralClkEdge = 0; msb_sr = 0; c_cs = 1; #5

        // Testing Write
        peripheralClkEdge = 0; msb_sr = 0; c_cs =0; #5
        peripheralClkEdge = 1; msb_sr = 0; c_cs =0; #2
        peripheralClkEdge = 0; msb_sr = 0; c_cs =0; #5
        peripheralClkEdge = 1; msb_sr = 0; c_cs =0; #2
        peripheralClkEdge = 0; msb_sr = 0; c_cs =0; #5
        peripheralClkEdge = 1; msb_sr = 0; c_cs =0; #2
        peripheralClkEdge = 0; msb_sr = 0; c_cs =0; #5
        peripheralClkEdge = 1; msb_sr = 0; c_cs =0; #2
        peripheralClkEdge = 0; msb_sr = 0; c_cs =0; #5
        peripheralClkEdge = 1; msb_sr = 0; c_cs =0; #2
        peripheralClkEdge = 0; msb_sr = 0; c_cs =0; #5
        peripheralClkEdge = 1; msb_sr = 0; c_cs =0; #2
        peripheralClkEdge = 0; msb_sr = 0; c_cs =0; #5
        peripheralClkEdge = 1; msb_sr = 0; c_cs =0; #2
        peripheralClkEdge = 0; msb_sr = 0; c_cs =0; #5
        peripheralClkEdge = 1; msb_sr = 0; c_cs =0; #2
        peripheralClkEdge = 0; msb_sr = 0; c_cs =0; #5
        peripheralClkEdge = 1; msb_sr = 0; c_cs =0; #2
        peripheralClkEdge = 0; msb_sr = 0; c_cs =0; #5
        peripheralClkEdge = 1; msb_sr = 0; c_cs =0; #2
        peripheralClkEdge = 0; msb_sr = 0; c_cs =0; #5
        peripheralClkEdge = 1; msb_sr = 0; c_cs =0; #2
        peripheralClkEdge = 0; msb_sr = 0; c_cs =0; #5
        peripheralClkEdge = 1; msb_sr = 0; c_cs =0; #2
        peripheralClkEdge = 0; msb_sr = 0; c_cs =0; #5
        peripheralClkEdge = 1; msb_sr = 0; c_cs =0; #2
        peripheralClkEdge = 0; msb_sr = 0; c_cs =0; #5
        peripheralClkEdge = 1; msb_sr = 0; c_cs =0; #2
        peripheralClkEdge = 0; msb_sr = 0; c_cs =0; #5
        peripheralClkEdge = 1; msb_sr = 0; c_cs =0; #2
        peripheralClkEdge = 0; msb_sr = 0; c_cs =0; #5
        peripheralClkEdge = 1; msb_sr = 0; c_cs =0; #2
        peripheralClkEdge = 0; msb_sr = 0; c_cs =0; #5
        peripheralClkEdge = 1; msb_sr = 0; c_cs =0; #2
        peripheralClkEdge = 0; msb_sr = 0; c_cs =0; #5


        // Testing Write
        peripheralClkEdge = 1; msb_sr = 1; c_cs =0; #2
        peripheralClkEdge = 0; msb_sr = 1; c_cs =0; #5
        peripheralClkEdge = 1; msb_sr = 1; c_cs =0; #2
        peripheralClkEdge = 0; msb_sr = 1; c_cs =0; #5
        peripheralClkEdge = 1; msb_sr = 1; c_cs =0; #2
        peripheralClkEdge = 0; msb_sr = 1; c_cs =0; #5
        peripheralClkEdge = 1; msb_sr = 1; c_cs =0; #2
        peripheralClkEdge = 0; msb_sr = 1; c_cs =0; #5
        peripheralClkEdge = 1; msb_sr = 1; c_cs =0; #2
        peripheralClkEdge = 0; msb_sr = 1; c_cs =0; #5
        peripheralClkEdge = 1; msb_sr = 1; c_cs =0; #2
        peripheralClkEdge = 0; msb_sr = 1; c_cs =0; #5
        peripheralClkEdge = 1; msb_sr = 1; c_cs =0; #2
        peripheralClkEdge = 0; msb_sr = 1; c_cs =0; #5
        peripheralClkEdge = 1; msb_sr = 1; c_cs =0; #2
        peripheralClkEdge = 0; msb_sr = 1; c_cs =0; #5
        peripheralClkEdge = 1; msb_sr = 1; c_cs =0; #2
        peripheralClkEdge = 0; msb_sr = 1; c_cs =0; #5
        peripheralClkEdge = 1; msb_sr = 1; c_cs =0; #2
        peripheralClkEdge = 0; msb_sr = 1; c_cs =0; #5
        peripheralClkEdge = 1; msb_sr = 1; c_cs =0; #2
        peripheralClkEdge = 0; msb_sr = 1; c_cs =0; #5
        peripheralClkEdge = 1; msb_sr = 1; c_cs =0; #2
        peripheralClkEdge = 0; msb_sr = 1; c_cs =0; #5
        peripheralClkEdge = 1; msb_sr = 1; c_cs =0; #2
        peripheralClkEdge = 0; msb_sr = 1; c_cs =0; #5
        peripheralClkEdge = 1; msb_sr = 1; c_cs =0; #2
        peripheralClkEdge = 0; msb_sr = 1; c_cs =0; #5
        peripheralClkEdge = 1; msb_sr = 1; c_cs =0; #2
        peripheralClkEdge = 0; msb_sr = 1; c_cs =0; #5
        peripheralClkEdge = 1; msb_sr = 1; c_cs =0; #2
        peripheralClkEdge = 0; msb_sr = 1; c_cs =0; #5
        peripheralClkEdge = 1; msb_sr = 1; c_cs =0; #2
        peripheralClkEdge = 0; msb_sr = 1; c_cs =0; #5
        peripheralClkEdge = 1; msb_sr = 1; c_cs =0; #2
        peripheralClkEdge = 0; msb_sr = 1; c_cs =0; #5
        peripheralClkEdge = 1; msb_sr = 1; c_cs =0; #2
        peripheralClkEdge = 0; msb_sr = 1; c_cs =0; #5
        peripheralClkEdge = 1; msb_sr = 1; c_cs =0; #2
        peripheralClkEdge = 0; msb_sr = 1; c_cs =0; #5
        peripheralClkEdge = 1; msb_sr = 1; c_cs =0; #2
        peripheralClkEdge = 0; msb_sr = 1; c_cs =0; #5


        // Testing cs off
        peripheralClkEdge = 1; msb_sr = 1; c_cs =1; #2
        peripheralClkEdge = 0; msb_sr = 1; c_cs =1; #5
        peripheralClkEdge = 1; msb_sr = 1; c_cs =1; #2
        peripheralClkEdge = 0; msb_sr = 1; c_cs =1; #5
        peripheralClkEdge = 1; msb_sr = 1; c_cs =1; #2
        peripheralClkEdge = 0; msb_sr = 1; c_cs =1; #5
        peripheralClkEdge = 1; msb_sr = 1; c_cs =1; #2
        peripheralClkEdge = 0; msb_sr = 1; c_cs =1; #5
        peripheralClkEdge = 1; msb_sr = 1; c_cs =1; #2
        peripheralClkEdge = 0; msb_sr = 1; c_cs =1; #5
        peripheralClkEdge = 1; msb_sr = 1; c_cs =1; #2
        peripheralClkEdge = 0; msb_sr = 1; c_cs =1; #5
        peripheralClkEdge = 1; msb_sr = 1; c_cs =1; #2
        peripheralClkEdge = 0; msb_sr = 1; c_cs =1; #5
        peripheralClkEdge = 1; msb_sr = 1; c_cs =1; #2
        peripheralClkEdge = 0; msb_sr = 1; c_cs =1; #5
        peripheralClkEdge = 1; msb_sr = 1; c_cs =1; #2
        peripheralClkEdge = 0; msb_sr = 1; c_cs =1; #5
        peripheralClkEdge = 1; msb_sr = 1; c_cs =1; #2
        peripheralClkEdge = 0; msb_sr = 1; c_cs =1; #5
        peripheralClkEdge = 1; msb_sr = 1; c_cs =1; #2
        peripheralClkEdge = 0; msb_sr = 1; c_cs =1; #5
        peripheralClkEdge = 1; msb_sr = 1; c_cs =1; #2
        peripheralClkEdge = 0; msb_sr = 1; c_cs =1; #5
        peripheralClkEdge = 1; msb_sr = 1; c_cs =1; #2
        peripheralClkEdge = 0; msb_sr = 1; c_cs =1; #5
        peripheralClkEdge = 1; msb_sr = 1; c_cs =1; #2
        peripheralClkEdge = 0; msb_sr = 1; c_cs =1; #5
        peripheralClkEdge = 1; msb_sr = 1; c_cs =1; #2
        peripheralClkEdge = 0; msb_sr = 1; c_cs =1; #5
        peripheralClkEdge = 1; msb_sr = 1; c_cs =1; #2
        peripheralClkEdge = 0; msb_sr = 1; c_cs =1; #5

        // Testing Write
        peripheralClkEdge = 1; msb_sr = 1; c_cs =0; #2
        peripheralClkEdge = 0; msb_sr = 1; c_cs =0; #5
        peripheralClkEdge = 1; msb_sr = 1; c_cs =0; #2
        peripheralClkEdge = 0; msb_sr = 1; c_cs =0; #5
        peripheralClkEdge = 1; msb_sr = 1; c_cs =0; #2
        peripheralClkEdge = 0; msb_sr = 1; c_cs =0; #5
        peripheralClkEdge = 1; msb_sr = 1; c_cs =0; #2
        peripheralClkEdge = 0; msb_sr = 1; c_cs =0; #5
        peripheralClkEdge = 1; msb_sr = 1; c_cs =0; #2
        peripheralClkEdge = 0; msb_sr = 1; c_cs =0; #5
        peripheralClkEdge = 1; msb_sr = 1; c_cs =0; #2
        peripheralClkEdge = 0; msb_sr = 1; c_cs =0; #5
        peripheralClkEdge = 1; msb_sr = 1; c_cs =0; #2
        peripheralClkEdge = 0; msb_sr = 1; c_cs =0; #5
        peripheralClkEdge = 1; msb_sr = 1; c_cs =0; #2
        peripheralClkEdge = 0; msb_sr = 1; c_cs =0; #5
        peripheralClkEdge = 1; msb_sr = 1; c_cs =0; #2
        peripheralClkEdge = 0; msb_sr = 1; c_cs =0; #5
        peripheralClkEdge = 1; msb_sr = 1; c_cs =0; #2
        peripheralClkEdge = 0; msb_sr = 1; c_cs =0; #5
        peripheralClkEdge = 1; msb_sr = 1; c_cs =0; #2
        peripheralClkEdge = 0; msb_sr = 1; c_cs =0; #5
        peripheralClkEdge = 1; msb_sr = 1; c_cs =0; #2
        peripheralClkEdge = 0; msb_sr = 1; c_cs =0; #5
    
      
        #10 $finish;
    end

endmodule

fsm.vcd
$date
	Wed Oct 26 01:28:15 2016
$end
$version
	Icarus Verilog
$end
$timescale
	1ps
$end
$scope module testfsm $end
$var wire 1 ! ADDR_WE $end
$var wire 1 " DM_WE $end
$var wire 1 # MISO_BUFF $end
$var wire 1 $ SR_WE $end
$var reg 1 % c_cs $end
$var reg 1 & clk $end
$var reg 1 ' msb_sr $end
$var reg 1 ( peripheralClkEdge $end
$scope module dut $end
$var wire 1 ) c_cs $end
$var wire 1 * clk $end
$var wire 1 + msb_sr $end
$var wire 1 , peripheralClkEdge $end
$var reg 1 - ADDR_WE $end
$var reg 1 . DM_WE $end
$var reg 1 / MISO_BUFF $end
$var reg 1 0 SR_WE $end
$var reg 4 1 counter [3:0] $end
$var reg 1 2 counter_reset $end
$var reg 8 3 state [7:0] $end
$upscope $end
$upscope $end
$enddefinitions $end
#0
$dumpvars
b1 3
02
b0 1
00
0/
0.
0-
0,
0+
1*
1)
0(
0'
1&
1%
0$
0#
0"
0!
$end
#1000
0&
0*
#2000
1&
1*
#3000
0&
0*
#4000
1&
1*
#5000
0&
0*
0%
0)
#6000
1&
1*
#7000
0&
0*
#8000
1&
1*
#9000
0&
0*
#10000
b1 1
1&
1*
1(
1,
#11000
0&
0*
#12000
1&
1*
0(
0,
#13000
0&
0*
#14000
1&
1*
#15000
0&
0*
#16000
1&
1*
#17000
0&
0*
1(
1,
#18000
b10 1
1&
1*
#19000
0&
0*
0(
0,
#20000
1&
1*
#21000
0&
0*
#22000
1&
1*
#23000
0&
0*
#24000
b11 1
1&
1*
1(
1,
#25000
0&
0*
#26000
1&
1*
0(
0,
#27000
0&
0*
#28000
1&
1*
#29000
0&
0*
#30000
1&
1*
#31000
0&
0*
1(
1,
#32000
b100 1
1&
1*
#33000
0&
0*
0(
0,
#34000
1&
1*
#35000
0&
0*
#36000
1&
1*
#37000
0&
0*
#38000
b101 1
1&
1*
1(
1,
#39000
0&
0*
#40000
1&
1*
0(
0,
#41000
0&
0*
#42000
1&
1*
#43000
0&
0*
#44000
1&
1*
#45000
0&
0*
1(
1,
#46000
b110 1
1&
1*
#47000
0&
0*
0(
0,
#48000
1&
1*
#49000
0&
0*
#50000
1&
1*
#51000
0&
0*
#52000
b111 1
1&
1*
1(
1,
#53000
0&
0*
#54000
1&
1*
0(
0,
#55000
0&
0*
#56000
1&
1*
#57000
0&
0*
#58000
1&
1*
#59000
0&
0*
1(
1,
#60000
b1000 1
1&
1*
#61000
0&
0*
0(
0,
#62000
b0 1
12
1-
1!
b10 3
1&
1*
#63000
0&
0*
#64000
0-
0!
b100000 3
02
1&
1*
#65000
0&
0*
#66000
b1 1
1&
1*
1(
1,
#67000
0&
0*
#68000
1&
1*
0(
0,
#69000
0&
0*
#70000
1&
1*
#71000
0&
0*
#72000
1&
1*
#73000
0&
0*
1(
1,
#74000
b10 1
1&
1*
#75000
0&
0*
0(
0,
#76000
1&
1*
#77000
0&
0*
#78000
1&
1*
#79000
0&
0*
#80000
b11 1
1&
1*
1(
1,
#81000
0&
0*
#82000
1&
1*
0(
0,
#83000
0&
0*
#84000
1&
1*
#85000
0&
0*
#86000
1&
1*
#87000
0&
0*
1(
1,
#88000
b100 1
1&
1*
#89000
0&
0*
0(
0,
#90000
1&
1*
#91000
0&
0*
#92000
1&
1*
#93000
0&
0*
#94000
b101 1
1&
1*
1(
1,
#95000
0&
0*
#96000
1&
1*
0(
0,
#97000
0&
0*
#98000
1&
1*
#99000
0&
0*
#100000
1&
1*
#101000
0&
0*
1(
1,
#102000
b110 1
1&
1*
#103000
0&
0*
0(
0,
#104000
1&
1*
#105000
0&
0*
#106000
1&
1*
#107000
0&
0*
#108000
b111 1
1&
1*
1(
1,
#109000
0&
0*
#110000
1&
1*
0(
0,
#111000
0&
0*
#112000
1&
1*
#113000
0&
0*
#114000
1&
1*
#115000
0&
0*
1(
1,
#116000
b1000 1
1&
1*
#117000
0&
0*
0(
0,
#118000
1.
1"
b1000000 3
1&
1*
#119000
0&
0*
#120000
b0 1
0.
0"
b10000000 3
1&
1*
#121000
0&
0*
#122000
b1 3
b1 1
1&
1*
1(
1,
#123000
0&
0*
#124000
1&
1*
0(
0,
#125000
0&
0*
#126000
1&
1*
#127000
0&
0*
#128000
1&
1*
#129000
0&
0*
1'
1+
1(
1,
#130000
b10 1
1&
1*
#131000
0&
0*
0(
0,
#132000
1&
1*
#133000
0&
0*
#134000
1&
1*
#135000
0&
0*
#136000
b11 1
1&
1*
1(
1,
#137000
0&
0*
#138000
1&
1*
0(
0,
#139000
0&
0*
#140000
1&
1*
#141000
0&
0*
#142000
1&
1*
#143000
0&
0*
1(
1,
#144000
b100 1
1&
1*
#145000
0&
0*
0(
0,
#146000
1&
1*
#147000
0&
0*
#148000
1&
1*
#149000
0&
0*
#150000
b101 1
1&
1*
1(
1,
#151000
0&
0*
#152000
1&
1*
0(
0,
#153000
0&
0*
#154000
1&
1*
#155000
0&
0*
#156000
1&
1*
#157000
0&
0*
1(
1,
#158000
b110 1
1&
1*
#159000
0&
0*
0(
0,
#160000
1&
1*
#161000
0&
0*
#162000
1&
1*
#163000
0&
0*
#164000
b111 1
1&
1*
1(
1,
#165000
0&
0*
#166000
1&
1*
0(
0,
#167000
0&
0*
#168000
1&
1*
#169000
0&
0*
#170000
1&
1*
#171000
0&
0*
1(
1,
#172000
b1000 1
1&
1*
#173000
0&
0*
0(
0,
#174000
b0 1
12
1-
1!
b10 3
1&
1*
#175000
0&
0*
#176000
0-
0!
b100 3
02
1&
1*
#177000
0&
0*
#178000
10
1$
b1000 3
b1 1
1&
1*
1(
1,
#179000
0&
0*
#180000
00
0$
1/
1#
b10000 3
1&
1*
0(
0,
#181000
0&
0*
#182000
1&
1*
#183000
0&
0*
#184000
1&
1*
#185000
0&
0*
1(
1,
#186000
b10 1
1&
1*
#187000
0&
0*
0(
0,
#188000
1&
1*
#189000
0&
0*
#190000
1&
1*
#191000
0&
0*
#192000
b11 1
1&
1*
1(
1,
#193000
0&
0*
#194000
1&
1*
0(
0,
#195000
0&
0*
#196000
1&
1*
#197000
0&
0*
#198000
1&
1*
#199000
0&
0*
1(
1,
#200000
b100 1
1&
1*
#201000
0&
0*
0(
0,
#202000
1&
1*
#203000
0&
0*
#204000
1&
1*
#205000
0&
0*
#206000
b101 1
1&
1*
1(
1,
#207000
0&
0*
#208000
1&
1*
0(
0,
#209000
0&
0*
#210000
1&
1*
#211000
0&
0*
#212000
1&
1*
#213000
0&
0*
1(
1,
#214000
b110 1
1&
1*
#215000
0&
0*
0(
0,
#216000
1&
1*
#217000
0&
0*
#218000
1&
1*
#219000
0&
0*
#220000
b111 1
1&
1*
1(
1,
#221000
0&
0*
#222000
1&
1*
0(
0,
#223000
0&
0*
#224000
1&
1*
#225000
0&
0*
#226000
1&
1*
#227000
0&
0*
1(
1,
#228000
b1000 1
1&
1*
#229000
0&
0*
0(
0,
#230000
b0 1
0/
0#
b10000000 3
1&
1*
#231000
0&
0*
#232000
b1 3
1&
1*
#233000
0&
0*
#234000
b1 1
1&
1*
1(
1,
#235000
0&
0*
#236000
1&
1*
0(
0,
#237000
0&
0*
#238000
1&
1*
#239000
0&
0*
#240000
1&
1*
#241000
0&
0*
1(
1,
#242000
b10 1
1&
1*
#243000
0&
0*
0(
0,
#244000
1&
1*
#245000
0&
0*
#246000
1&
1*
#247000
0&
0*
#248000
b11 1
1&
1*
1(
1,
#249000
0&
0*
#250000
1&
1*
0(
0,
#251000
0&
0*
#252000
1&
1*
#253000
0&
0*
#254000
1&
1*
#255000
0&
0*
1(
1,
#256000
b100 1
1&
1*
#257000
0&
0*
0(
0,
#258000
1&
1*
#259000
0&
0*
#260000
1&
1*
#261000
0&
0*
#262000
b101 1
1&
1*
1(
1,
#263000
0&
0*
#264000
1&
1*
0(
0,
#265000
0&
0*
#266000
1&
1*
#267000
0&
0*
#268000
1&
1*
#269000
0&
0*
1(
1,
#270000
b110 1
1&
1*
#271000
0&
0*
0(
0,
#272000
1&
1*
#273000
0&
0*
#274000
1&
1*
#275000
0&
0*
#276000
b0 1
1&
1*
1%
1)
1(
1,
#277000
0&
0*
#278000
1&
1*
0(
0,
#279000
0&
0*
#280000
1&
1*
#281000
0&
0*
#282000
1&
1*
#283000
0&
0*
1(
1,
#284000
b0 1
1&
1*
#285000
0&
0*
0(
0,
#286000
1&
1*
#287000
0&
0*
#288000
1&
1*
#289000
0&
0*
#290000
b0 1
1&
1*
1(
1,
#291000
0&
0*
#292000
1&
1*
0(
0,
#293000
0&
0*
#294000
1&
1*
#295000
0&
0*
#296000
1&
1*
#297000
0&
0*
1(
1,
#298000
b0 1
1&
1*
#299000
0&
0*
0(
0,
#300000
1&
1*
#301000
0&
0*
#302000
1&
1*
#303000
0&
0*
#304000
b0 1
1&
1*
1(
1,
#305000
0&
0*
#306000
1&
1*
0(
0,
#307000
0&
0*
#308000
1&
1*
#309000
0&
0*
#310000
1&
1*
#311000
0&
0*
1(
1,
#312000
b0 1
1&
1*
#313000
0&
0*
0(
0,
#314000
1&
1*
#315000
0&
0*
#316000
1&
1*
#317000
0&
0*
#318000
b0 1
1&
1*
1(
1,
#319000
0&
0*
#320000
1&
1*
0(
0,
#321000
0&
0*
#322000
1&
1*
#323000
0&
0*
#324000
1&
1*
#325000
0&
0*
1(
1,
#326000
b0 1
1&
1*
#327000
0&
0*
0(
0,
#328000
1&
1*
#329000
0&
0*
#330000
1&
1*
#331000
0&
0*
#332000
b0 1
1&
1*
1(
1,
#333000
0&
0*
#334000
1&
1*
0(
0,
#335000
0&
0*
#336000
1&
1*
#337000
0&
0*
#338000
1&
1*
#339000
0&
0*
1(
1,
#340000
b0 1
1&
1*
#341000
0&
0*
0(
0,
#342000
1&
1*
#343000
0&
0*
#344000
1&
1*
#345000
0&
0*
#346000
b0 1
1&
1*
1(
1,
#347000
0&
0*
#348000
1&
1*
0(
0,
#349000
0&
0*
#350000
1&
1*
#351000
0&
0*
#352000
1&
1*
#353000
0&
0*
1(
1,
#354000
b0 1
1&
1*
#355000
0&
0*
0(
0,
#356000
1&
1*
#357000
0&
0*
#358000
1&
1*
#359000
0&
0*
#360000
b0 1
1&
1*
1(
1,
#361000
0&
0*
#362000
1&
1*
0(
0,
#363000
0&
0*
#364000
1&
1*
#365000
0&
0*
#366000
1&
1*
#367000
0&
0*
1(
1,
#368000
b0 1
1&
1*
#369000
0&
0*
0(
0,
#370000
1&
1*
#371000
0&
0*
#372000
1&
1*
#373000
0&
0*
#374000
b0 1
1&
1*
1(
1,
#375000
0&
0*
#376000
1&
1*
0(
0,
#377000
0&
0*
#378000
1&
1*
#379000
0&
0*
#380000
1&
1*
#381000
0&
0*
1(
1,
#382000
b0 1
1&
1*
#383000
0&
0*
0(
0,
#384000
1&
1*
#385000
0&
0*
#386000
1&
1*
#387000
0&
0*
#388000
b1 1
1&
1*
0%
0)
1(
1,
#389000
0&
0*
#390000
1&
1*
0(
0,
#391000
0&
0*
#392000
1&
1*
#393000
0&
0*
#394000
1&
1*
#395000
0&
0*
1(
1,
#396000
b10 1
1&
1*
#397000
0&
0*
0(
0,
#398000
1&
1*
#399000
0&
0*
#400000
1&
1*
#401000
0&
0*
#402000
b11 1
1&
1*
1(
1,
#403000
0&
0*
#404000
1&
1*
0(
0,
#405000
0&
0*
#406000
1&
1*
#407000
0&
0*
#408000
1&
1*
#409000
0&
0*
1(
1,
#410000
b100 1
1&
1*
#411000
0&
0*
0(
0,
#412000
1&
1*
#413000
0&
0*
#414000
1&
1*
#415000
0&
0*
#416000
b101 1
1&
1*
1(
1,
#417000
0&
0*
#418000
1&
1*
0(
0,
#419000
0&
0*
#420000
1&
1*
#421000
0&
0*
#422000
1&
1*
#423000
0&
0*
1(
1,
#424000
b110 1
1&
1*
#425000
0&
0*
0(
0,
#426000
1&
1*
#427000
0&
0*
#428000
1&
1*
#429000
0&
0*
#430000
b111 1
1&
1*
1(
1,
#431000
0&
0*
#432000
1&
1*
0(
0,
#433000
0&
0*
#434000
1&
1*
#435000
0&
0*
#436000
1&
1*
#437000
0&
0*
1(
1,
#438000
b1000 1
1&
1*
#439000
0&
0*
0(
0,
#440000
b0 1
12
1-
1!
b10 3
1&
1*
#441000
0&
0*
#442000
0-
0!
b100 3
02
1&
1*
#443000
0&
0*
#444000
10
1$
b1000 3
b1 1
1&
1*
1(
1,
#445000
0&
0*
#446000
00
0$
1/
1#
b10000 3
1&
1*
0(
0,
#447000
0&
0*
#448000
1&
1*
#449000
0&
0*
#450000
1&
1*
#451000
0&
0*
1(
1,
#452000
b10 1
1&
1*
#453000
0&
0*
0(
0,
#454000
1&
1*
#455000
0&
0*
#456000
1&
1*
#457000
0&
0*
#458000
b11 1
1&
1*
1(
1,
#459000
0&
0*
#460000
1&
1*
0(
0,
#461000
0&
0*
#462000
1&
1*
#463000
0&
0*
#464000
1&
1*
#465000
0&
0*
1(
1,
#466000
b100 1
1&
1*
#467000
0&
0*
0(
0,
