fsm_pk.v
module fsm
(
input clk,
input msb_sr,	// most significant bit shift register output
input c_cs,		// conditioned chip select signal put thru input conditioner
input peripheralClkEdge,	// peripheral clockedge of sclk
output reg MISO_BUFF, 			// miso output enable
output reg DM_WE,				// Data Memory Write Enable
output reg ADDR_WE,				// Address Write Enable (for address latch)
output reg SR_WE				// Shift Register Write Enable
);
reg[7:0] state;

localparam GET = 8'b00000001,
		   GOT = 8'b00000010,
		   READ1 = 8'b00000100,
		   READ2 = 8'b00001000,
		   READ3 = 8'b00010000,
		   WRITE1 = 8'b00100000,
		   WRITE2 = 8'b01000000,
		   DONE = 8'b10000000;
reg [3:0] counter;
reg counter_reset;
reg reset_flg;

initial begin
counter = 4'b0000;
counter_reset = 0;
reset_flg = 0;
end



always @(posedge clk) begin

	if (counter_reset) begin
	counter_reset <= 0;
	counter = 4'b0000;
	reset_flg <= 1;
	
	end

	
	if (c_cs) begin
		state <= GET;
		counter <= 4'b0000;
		MISO_BUFF = 0;
		DM_WE =0;
		ADDR_WE =0;
		SR_WE =0;
	end

	if (peripheralClkEdge && !counter_reset) begin
		counter <= counter + 1;
	end

	else begin
		case (state)
			GET: begin
				if (counter==4'b1000) begin
					state <= GOT;
				end
				else begin
					state <= GET;
					//counter <= counter + 4'b0001;
				end
			end

			GOT: begin
				if (msb_sr==1) begin
					state <= READ1;
				end
				else begin
					if (!msb_sr && reset_flg) begin
						state <= WRITE1;
						reset_flg <=0;
					end
				end
			end

			READ1: begin
				state <= READ2;
			end

			READ2: begin
				state <= READ3;
			end

			READ3: begin
				if (counter == 4'b1000) begin
					state <= DONE;
				end
				else begin
					state <= READ3;
					//counter <= counter + 1;
				end
			end

			WRITE1: begin
				if (counter == 4'b1000) begin
					state <= WRITE2;
					counter_reset <= 1;
				end
				else begin
					counter_reset <=0;
					state <= WRITE1;
					//counter <= counter + 1;
				end
			end

			WRITE2: begin
				state <= DONE;
			end

			DONE: begin
				if (reset_flg); begin
					state <= GET;
					reset_flg <=0;
				end
			end
		endcase
//end // @ peripheralclkedge
end
end
always @(state) begin
	case (state)
		GET: begin
		end

		GOT: begin
			ADDR_WE <= 1;
			counter_reset <= 1;
		end

		READ1: begin

		end

		READ2: begin
			SR_WE <= 1;
		end

		READ3: begin
			MISO_BUFF <=1;
		end

		WRITE1: begin
		end

		WRITE2: begin
			DM_WE <= 1;
		end

		DONE: begin
			MISO_BUFF <= 0;
			DM_WE <=0;
			ADDR_WE <=0;
			SR_WE <=0;
			counter_reset <= 1;
		end
	endcase
end // @ state

endmodule

fsm_pk.t.v
//------------------------------------------------------------------------
// Shift Register test bench
//------------------------------------------------------------------------
`timescale 1ns / 1ps

`include "fsm_pk.v"

module testfsm();
    reg clk;
    reg msb_sr;   // most significant bit shift register output
    reg c_cs;     // conditioned chip select signal put thru input conditioner
    reg peripheralClkEdge;    // peripheral clockedge of sclk
//    reg clk;                  // clk
    wire MISO_BUFF;           // miso output enable
    wire DM_WE;               // Data Memory Write Enable
    wire ADDR_WE;             // Address Write Enable (for address latch)
    wire SR_WE;                // Shift Register Write Enable

    // Instantiate with parameter width = 8
    fsm dut( 
    		           .clk(clk),
    		           .msb_sr(msb_sr), 
    		           .c_cs(c_cs), 
                       .peripheralClkEdge(peripheralClkEdge),
    		           .MISO_BUFF(MISO_BUFF), 
    		           .DM_WE(DM_WE),
                       .ADDR_WE(ADDR_WE),
    		           .SR_WE(SR_WE));
    always begin
    #1 clk = ~clk;
    #2 peripheralClkEdge= ~peripheralClkEdge;
    end

    initial begin
    	// Your Test Code
        $dumpfile("fsm_pk.vcd");
        $dumpvars();

        $display(" clk  |   pclk   |  pload |     pin      |  sin  |      pout     |  sout  |  expected");
        
        // Initial Conditions time = 0
        //clk=1; peripheralClkEdge = 0; msb_sr = 0; c_cs = 1; #2
        // Now we will assign values for different test cases
        clk = 0; peripheralClkEdge = 0; msb_sr = 1; c_cs =1; #4
        peripheralClkEdge = 0; msb_sr = 0; c_cs =0; #2
        peripheralClkEdge = 1; msb_sr = 0; c_cs =0; #2
        peripheralClkEdge = 0; msb_sr = 0; c_cs =0; #2
        peripheralClkEdge = 1; msb_sr = 0; c_cs =0; #2
        peripheralClkEdge = 0; msb_sr = 0; c_cs =0; #2
        peripheralClkEdge = 1; msb_sr = 0; c_cs =0; #2
        peripheralClkEdge = 0; msb_sr = 0; c_cs =0; #2
        peripheralClkEdge = 1; msb_sr = 0; c_cs =0; #2
        peripheralClkEdge = 0; msb_sr = 0; c_cs =0; #2
        peripheralClkEdge = 1; msb_sr = 0; c_cs =0; #2
        peripheralClkEdge = 0; msb_sr = 0; c_cs =0; #2
        peripheralClkEdge = 1; msb_sr = 0; c_cs =0; #2
        peripheralClkEdge = 0; msb_sr = 0; c_cs =0; #2
        peripheralClkEdge = 1; msb_sr = 0; c_cs =0; #2
        peripheralClkEdge = 0; msb_sr = 0; c_cs =0; #2
        peripheralClkEdge = 1; msb_sr = 0; c_cs =0; #2
        peripheralClkEdge = 0; msb_sr = 0; c_cs =0; #2
        peripheralClkEdge = 1; msb_sr = 0; c_cs =0; #2
        peripheralClkEdge = 0; msb_sr = 0; c_cs =0; #2
        peripheralClkEdge = 1; msb_sr = 0; c_cs =0; #2
        peripheralClkEdge = 0; msb_sr = 0; c_cs =0; #2
        peripheralClkEdge = 1; msb_sr = 0; c_cs =0; #2
        peripheralClkEdge = 0; msb_sr = 0; c_cs =0; #2
        peripheralClkEdge = 1; msb_sr = 0; c_cs =0; #2
        peripheralClkEdge = 0; msb_sr = 0; c_cs =0; #2
        peripheralClkEdge = 1; msb_sr = 0; c_cs =0; #2
        peripheralClkEdge = 0; msb_sr = 0; c_cs =0; #2
        peripheralClkEdge = 1; msb_sr = 0; c_cs =0; #2
        peripheralClkEdge = 0; msb_sr = 0; c_cs =0; #2
        peripheralClkEdge = 1; msb_sr = 0; c_cs =0; #2
        peripheralClkEdge = 0; msb_sr = 0; c_cs =0; #2
        peripheralClkEdge = 1; msb_sr = 0; c_cs =0; #2
        peripheralClkEdge = 0; msb_sr = 0; c_cs =0; #2
        peripheralClkEdge = 1; msb_sr = 0; c_cs =0; #2
        peripheralClkEdge = 0; msb_sr = 0; c_cs =0; #2
        peripheralClkEdge = 1; msb_sr = 0; c_cs =0; #2
        peripheralClkEdge = 0; msb_sr = 0; c_cs =0; #2
        peripheralClkEdge = 1; msb_sr = 0; c_cs =0; #2
        peripheralClkEdge = 0; msb_sr = 0; c_cs =0; #2
        peripheralClkEdge = 1; msb_sr = 0; c_cs =0; #2
        peripheralClkEdge = 0; msb_sr = 0; c_cs =0; #2
        peripheralClkEdge = 1; msb_sr = 0; c_cs =0; #2
        peripheralClkEdge = 0; msb_sr = 0; c_cs =0; #2
        peripheralClkEdge = 1; msb_sr = 0; c_cs =0; #2
        peripheralClkEdge = 0; msb_sr = 0; c_cs =0; #2
        peripheralClkEdge = 1; msb_sr = 0; c_cs =0; #2
        peripheralClkEdge = 0; msb_sr = 0; c_cs =0; #2
        peripheralClkEdge = 1; msb_sr = 0; c_cs =0; #2
        peripheralClkEdge = 0; msb_sr = 0; c_cs =0; #2
        peripheralClkEdge = 1; msb_sr = 0; c_cs =0; #2
        peripheralClkEdge = 0; msb_sr = 0; c_cs =0; #2
        peripheralClkEdge = 1; msb_sr = 0; c_cs =0; #2
        peripheralClkEdge = 0; msb_sr = 0; c_cs =0; #2
        peripheralClkEdge = 1; msb_sr = 0; c_cs =0; #2
        peripheralClkEdge = 0; msb_sr = 0; c_cs =0; #2
        peripheralClkEdge = 1; msb_sr = 0; c_cs =0; #2
        peripheralClkEdge = 0; msb_sr = 0; c_cs =0; #2
        peripheralClkEdge = 1; msb_sr = 0; c_cs =0; #2
        peripheralClkEdge = 0; msb_sr = 0; c_cs =0; #2
        peripheralClkEdge = 1; msb_sr = 0; c_cs =0; #2
        peripheralClkEdge = 0; msb_sr = 0; c_cs =0; #2
        peripheralClkEdge = 1; msb_sr = 0; c_cs =0; #2
        peripheralClkEdge = 0; msb_sr = 0; c_cs =0; #2
        peripheralClkEdge = 1; msb_sr = 0; c_cs =0; #2
        peripheralClkEdge = 0; msb_sr = 0; c_cs =0; #2
        peripheralClkEdge = 1; msb_sr = 0; c_cs =0; #2
        peripheralClkEdge = 0; msb_sr = 0; c_cs =0; #2
        peripheralClkEdge = 1; msb_sr = 0; c_cs =0; #2
        peripheralClkEdge = 0; msb_sr = 0; c_cs =0; #2
        peripheralClkEdge = 1; msb_sr = 0; c_cs =0; #2
        peripheralClkEdge = 0; msb_sr = 0; c_cs =0; #2
        peripheralClkEdge = 1; msb_sr = 0; c_cs =0; #2
        peripheralClkEdge = 0; msb_sr = 0; c_cs =0; #2
        peripheralClkEdge = 1; msb_sr = 0; c_cs =0; #2
        peripheralClkEdge = 0; msb_sr = 0; c_cs =0; #2
        peripheralClkEdge = 1; msb_sr = 0; c_cs =0; #2
        peripheralClkEdge = 0; msb_sr = 0; c_cs =0; #2
        peripheralClkEdge = 1; msb_sr = 0; c_cs =0; #2
        peripheralClkEdge = 0; msb_sr = 0; c_cs =0; #2
        peripheralClkEdge = 1; msb_sr = 0; c_cs =0; #2
        peripheralClkEdge = 0; msb_sr = 0; c_cs =0; #2
        peripheralClkEdge = 1; msb_sr = 0; c_cs =0; #2
        peripheralClkEdge = 0; msb_sr = 0; c_cs =0; #2
        peripheralClkEdge = 1; msb_sr = 0; c_cs =0; #2
        peripheralClkEdge = 0; msb_sr = 0; c_cs =0; #2
        peripheralClkEdge = 1; msb_sr = 0; c_cs =0; #2
        peripheralClkEdge = 0; msb_sr = 0; c_cs =0; #2
        peripheralClkEdge = 1; msb_sr = 0; c_cs =0; #2
        peripheralClkEdge = 0; msb_sr = 0; c_cs =0; #2
        peripheralClkEdge = 1; msb_sr = 0; c_cs =0; #2
        peripheralClkEdge = 0; msb_sr = 0; c_cs =0; #2
        peripheralClkEdge = 1; msb_sr = 0; c_cs =0; #2
        peripheralClkEdge = 0; msb_sr = 0; c_cs =0; #2
        peripheralClkEdge = 1; msb_sr = 0; c_cs =0; #2
        peripheralClkEdge = 0; msb_sr = 0; c_cs =0; #2
        peripheralClkEdge = 1; msb_sr = 0; c_cs =0; #2
        peripheralClkEdge = 0; msb_sr = 0; c_cs =0; #2
        peripheralClkEdge = 1; msb_sr = 0; c_cs =0; #2
        peripheralClkEdge = 0; msb_sr = 0; c_cs =0; #2
        peripheralClkEdge = 1; msb_sr = 0; c_cs =0; #2
        peripheralClkEdge = 0; msb_sr = 0; c_cs =0; #2
        peripheralClkEdge = 1; msb_sr = 0; c_cs =0; #2
        peripheralClkEdge = 0; msb_sr = 0; c_cs =0; #2
        peripheralClkEdge = 1; msb_sr = 0; c_cs =0; #2
        peripheralClkEdge = 0; msb_sr = 0; c_cs =0; #2
        peripheralClkEdge = 1; msb_sr = 0; c_cs =0; #2
        peripheralClkEdge = 0; msb_sr = 0; c_cs =0; #2
        peripheralClkEdge = 1; msb_sr = 0; c_cs =0; #2
        peripheralClkEdge = 0; msb_sr = 0; c_cs =0; #2
        peripheralClkEdge = 1; msb_sr = 0; c_cs =0; #2
        peripheralClkEdge = 0; msb_sr = 0; c_cs =0; #2
        peripheralClkEdge = 1; msb_sr = 0; c_cs =0; #2
        peripheralClkEdge = 0; msb_sr = 0; c_cs =0; #2
        peripheralClkEdge = 1; msb_sr = 0; c_cs =0; #2
        peripheralClkEdge = 0; msb_sr = 0; c_cs =0; #2
        peripheralClkEdge = 1; msb_sr = 0; c_cs =0; #2
        peripheralClkEdge = 0; msb_sr = 0; c_cs =0; #2
        peripheralClkEdge = 1; msb_sr = 0; c_cs =0; #2
        peripheralClkEdge = 0; msb_sr = 0; c_cs =0; #2
        peripheralClkEdge = 1; msb_sr = 0; c_cs =0; #2
        

clk = 0; peripheralClkEdge = 0; msb_sr = 1; c_cs =1; #4
        peripheralClkEdge = 0; msb_sr = 1; c_cs =0; #2
        peripheralClkEdge = 1; msb_sr = 1; c_cs =0; #2
        peripheralClkEdge = 0; msb_sr = 1; c_cs =0; #2
        peripheralClkEdge = 1; msb_sr = 1; c_cs =0; #2
        peripheralClkEdge = 0; msb_sr = 1; c_cs =0; #2
        peripheralClkEdge = 1; msb_sr = 1; c_cs =0; #2
        peripheralClkEdge = 0; msb_sr = 1; c_cs =0; #2
        peripheralClkEdge = 1; msb_sr = 1; c_cs =0; #2
        peripheralClkEdge = 0; msb_sr = 1; c_cs =0; #2
        peripheralClkEdge = 1; msb_sr = 1; c_cs =0; #2
        peripheralClkEdge = 0; msb_sr = 1; c_cs =0; #2
        peripheralClkEdge = 1; msb_sr = 1; c_cs =0; #2
        peripheralClkEdge = 0; msb_sr = 1; c_cs =0; #2
        peripheralClkEdge = 1; msb_sr = 1; c_cs =0; #2
        peripheralClkEdge = 0; msb_sr = 1; c_cs =0; #2
        peripheralClkEdge = 1; msb_sr = 1; c_cs =0; #2
        peripheralClkEdge = 0; msb_sr = 1; c_cs =0; #2
        peripheralClkEdge = 1; msb_sr = 1; c_cs =0; #2
        peripheralClkEdge = 0; msb_sr = 1; c_cs =0; #2
        peripheralClkEdge = 1; msb_sr = 1; c_cs =0; #2
        peripheralClkEdge = 0; msb_sr = 1; c_cs =0; #2
        peripheralClkEdge = 1; msb_sr = 1; c_cs =0; #2
        peripheralClkEdge = 0; msb_sr = 1; c_cs =0; #2
        peripheralClkEdge = 1; msb_sr = 1; c_cs =0; #2
        peripheralClkEdge = 0; msb_sr = 1; c_cs =0; #2
        peripheralClkEdge = 1; msb_sr = 1; c_cs =0; #2
        peripheralClkEdge = 0; msb_sr = 1; c_cs =0; #2
        peripheralClkEdge = 1; msb_sr = 1; c_cs =0; #2
        peripheralClkEdge = 0; msb_sr = 1; c_cs =0; #2
        peripheralClkEdge = 1; msb_sr = 1; c_cs =0; #2
        peripheralClkEdge = 0; msb_sr = 1; c_cs =0; #2
        peripheralClkEdge = 1; msb_sr = 1; c_cs =0; #2
        peripheralClkEdge = 0; msb_sr = 1; c_cs =0; #2
        peripheralClkEdge = 1; msb_sr = 1; c_cs =0; #2
        peripheralClkEdge = 0; msb_sr = 1; c_cs =0; #2
        peripheralClkEdge = 1; msb_sr = 1; c_cs =0; #2
        peripheralClkEdge = 0; msb_sr = 1; c_cs =0; #2
        peripheralClkEdge = 1; msb_sr = 1; c_cs =0; #2
        peripheralClkEdge = 0; msb_sr = 1; c_cs =0; #2
        peripheralClkEdge = 1; msb_sr = 1; c_cs =0; #2
        peripheralClkEdge = 0; msb_sr = 1; c_cs =0; #2
        peripheralClkEdge = 1; msb_sr = 1; c_cs =0; #2
        peripheralClkEdge = 0; msb_sr = 1; c_cs =0; #2
        peripheralClkEdge = 1; msb_sr = 1; c_cs =0; #2
        peripheralClkEdge = 0; msb_sr = 1; c_cs =0; #2
        peripheralClkEdge = 1; msb_sr = 1; c_cs =0; #2
        peripheralClkEdge = 0; msb_sr = 1; c_cs =0; #2
        peripheralClkEdge = 1; msb_sr = 1; c_cs =0; #2
        peripheralClkEdge = 0; msb_sr = 1; c_cs =0; #2
        peripheralClkEdge = 1; msb_sr = 1; c_cs =0; #2
        peripheralClkEdge = 0; msb_sr = 1; c_cs =0; #2
        peripheralClkEdge = 1; msb_sr = 1; c_cs =0; #2
        peripheralClkEdge = 0; msb_sr = 1; c_cs =0; #2
        peripheralClkEdge = 1; msb_sr = 1; c_cs =0; #2
        peripheralClkEdge = 0; msb_sr = 1; c_cs =0; #2
        peripheralClkEdge = 1; msb_sr = 1; c_cs =0; #2
        peripheralClkEdge = 0; msb_sr = 1; c_cs =0; #2
        peripheralClkEdge = 1; msb_sr = 1; c_cs =0; #2
        peripheralClkEdge = 0; msb_sr = 1; c_cs =0; #2
        peripheralClkEdge = 1; msb_sr = 1; c_cs =0; #2
        peripheralClkEdge = 0; msb_sr = 1; c_cs =0; #2
        peripheralClkEdge = 1; msb_sr = 1; c_cs =0; #2
        peripheralClkEdge = 0; msb_sr = 1; c_cs =0; #2
        peripheralClkEdge = 1; msb_sr = 1; c_cs =0; #2
        peripheralClkEdge = 0; msb_sr = 1; c_cs =0; #2
        peripheralClkEdge = 1; msb_sr = 1; c_cs =0; #2
        peripheralClkEdge = 0; msb_sr = 1; c_cs =0; #2
        peripheralClkEdge = 1; msb_sr = 1; c_cs =0; #2
        peripheralClkEdge = 0; msb_sr = 1; c_cs =0; #2
        peripheralClkEdge = 1; msb_sr = 1; c_cs =0; #2
        peripheralClkEdge = 0; msb_sr = 1; c_cs =0; #2
        peripheralClkEdge = 1; msb_sr = 1; c_cs =0; #2
        peripheralClkEdge = 0; msb_sr = 1; c_cs =0; #2
        peripheralClkEdge = 1; msb_sr = 1; c_cs =0; #2
        peripheralClkEdge = 0; msb_sr = 1; c_cs =0; #2
        peripheralClkEdge = 1; msb_sr = 1; c_cs =0; #2
        peripheralClkEdge = 0; msb_sr = 1; c_cs =0; #2
        peripheralClkEdge = 1; msb_sr = 1; c_cs =0; #2
        peripheralClkEdge = 0; msb_sr = 1; c_cs =0; #2
        peripheralClkEdge = 1; msb_sr = 1; c_cs =0; #2
        peripheralClkEdge = 0; msb_sr = 1; c_cs =0; #2
        peripheralClkEdge = 1; msb_sr = 1; c_cs =0; #2
        peripheralClkEdge = 0; msb_sr = 1; c_cs =0; #2
        peripheralClkEdge = 1; msb_sr = 1; c_cs =0; #2
        peripheralClkEdge = 0; msb_sr = 1; c_cs =0; #2
        peripheralClkEdge = 1; msb_sr = 1; c_cs =0; #2
        peripheralClkEdge = 0; msb_sr = 1; c_cs =0; #2
        peripheralClkEdge = 1; msb_sr = 1; c_cs =0; #2
        peripheralClkEdge = 0; msb_sr = 1; c_cs =0; #2
        peripheralClkEdge = 1; msb_sr = 1; c_cs =0; #2
        peripheralClkEdge = 0; msb_sr = 1; c_cs =0; #2
        peripheralClkEdge = 1; msb_sr = 1; c_cs =0; #2
        peripheralClkEdge = 0; msb_sr = 1; c_cs =0; #2
        peripheralClkEdge = 1; msb_sr = 1; c_cs =0; #2
        peripheralClkEdge = 0; msb_sr = 1; c_cs =0; #2
        peripheralClkEdge = 1; msb_sr = 1; c_cs =0; #2
        peripheralClkEdge = 0; msb_sr = 1; c_cs =0; #2
        peripheralClkEdge = 1; msb_sr = 1; c_cs =0; #2
        peripheralClkEdge = 0; msb_sr = 1; c_cs =0; #2
        peripheralClkEdge = 1; msb_sr = 1; c_cs =0; #2

        #20 $finish;
    end

endmodule

fsm_pk.vcd
$date
	Tue Oct 25 04:31:26 2016
$end
$version
	Icarus Verilog
$end
$timescale
	1ps
$end
$scope module testfsm $end
$var wire 1 ! ADDR_WE $end
$var wire 1 " DM_WE $end
$var wire 1 # MISO_BUFF $end
$var wire 1 $ SR_WE $end
$var reg 1 % c_cs $end
$var reg 1 & clk $end
$var reg 1 ' msb_sr $end
$var reg 1 ( peripheralClkEdge $end
$scope module dut $end
$var wire 1 ) c_cs $end
$var wire 1 * clk $end
$var wire 1 + msb_sr $end
$var wire 1 , peripheralClkEdge $end
$var reg 1 - ADDR_WE $end
$var reg 1 . DM_WE $end
$var reg 1 / MISO_BUFF $end
$var reg 1 0 SR_WE $end
$var reg 4 1 counter [3:0] $end
$var reg 1 2 counter_reset $end
$var reg 1 3 reset_flg $end
$var reg 8 4 state [7:0] $end
$upscope $end
$upscope $end
$enddefinitions $end
#0
$dumpvars
bx 4
03
02
b0 1
x0
x/
x.
x-
0,
1+
0*
1)
0(
1'
0&
1%
x$
x#
x"
x!
$end
#1000
b1 4
00
0$
0-
0!
0.
0"
0/
0#
1&
1*
#3000
1(
1,
#4000
0&
0*
0%
0)
0'
0+
0(
0,
#6000
0(
0,
#7000
1&
1*
#9000
1(
1,
#10000
0&
0*
#12000
1(
1,
#13000
b1 1
1&
1*
#15000
0(
0,
#16000
0&
0*
#18000
0(
0,
#19000
1&
1*
#21000
1(
1,
#22000
0&
0*
#24000
1(
1,
#25000
b10 1
1&
1*
#27000
0(
0,
#28000
0&
0*
#30000
0(
0,
#31000
1&
1*
#33000
1(
1,
#34000
0&
0*
#36000
1(
1,
#37000
b11 1
1&
1*
#39000
0(
0,
#40000
0&
0*
#42000
0(
0,
#43000
1&
1*
#45000
1(
1,
#46000
0&
0*
#48000
1(
1,
#49000
b100 1
1&
1*
#51000
0(
0,
#52000
0&
0*
#54000
0(
0,
#55000
1&
1*
#57000
1(
1,
#58000
0&
0*
#60000
1(
1,
#61000
b101 1
1&
1*
#63000
0(
0,
#64000
0&
0*
#66000
0(
0,
#67000
1&
1*
#69000
1(
1,
#70000
0&
0*
#72000
1(
1,
#73000
b110 1
1&
1*
#75000
0(
0,
#76000
0&
0*
#78000
0(
0,
#79000
1&
1*
#81000
1(
1,
#82000
0&
0*
#84000
1(
1,
#85000
b111 1
1&
1*
#87000
0(
0,
#88000
0&
0*
#90000
0(
0,
#91000
1&
1*
#93000
1(
1,
#94000
0&
0*
#96000
1(
1,
#97000
b1000 1
1&
1*
#99000
0(
0,
#100000
0&
0*
#102000
0(
0,
#103000
12
1-
1!
b10 4
1&
1*
#105000
1(
1,
#106000
0&
0*
#108000
1(
1,
#109000
13
02
b0 1
1&
1*
#111000
0(
0,
#112000
0&
0*
#114000
0(
0,
#115000
03
b100000 4
1&
1*
#117000
1(
1,
#118000
0&
0*
#120000
1(
1,
#121000
b1 1
1&
1*
#123000
0(
0,
#124000
0&
0*
#126000
0(
0,
#127000
1&
1*
#129000
1(
1,
#130000
0&
0*
#132000
1(
1,
#133000
b10 1
1&
1*
#135000
0(
0,
#136000
0&
0*
#138000
0(
0,
#139000
1&
1*
#141000
1(
1,
#142000
0&
0*
#144000
1(
1,
#145000
b11 1
1&
1*
#147000
0(
0,
#148000
0&
0*
#150000
0(
0,
#151000
1&
1*
#153000
1(
1,
#154000
0&
0*
#156000
1(
1,
#157000
b100 1
1&
1*
#159000
0(
0,
#160000
0&
0*
#162000
0(
0,
#163000
1&
1*
#165000
1(
1,
#166000
0&
0*
#168000
1(
1,
#169000
b101 1
1&
1*
#171000
0(
0,
#172000
0&
0*
#174000
0(
0,
#175000
1&
1*
#177000
1(
1,
#178000
0&
0*
#180000
1(
1,
#181000
b110 1
1&
1*
#183000
0(
0,
#184000
0&
0*
#186000
0(
0,
#187000
1&
1*
#189000
1(
1,
#190000
0&
0*
#192000
1(
1,
#193000
b111 1
1&
1*
#195000
0(
0,
#196000
0&
0*
#198000
0(
0,
#199000
1&
1*
#201000
1(
1,
#202000
0&
0*
#204000
1(
1,
#205000
b1000 1
1&
1*
#207000
0(
0,
#208000
0&
0*
#210000
0(
0,
#211000
1.
1"
12
b1000000 4
1&
1*
#213000
1(
1,
#214000
0&
0*
#216000
1(
1,
#217000
0-
0!
0.
0"
b10000000 4
13
12
b0 1
1&
1*
#219000
0(
0,
#220000
0&
0*
#222000
0(
0,
#223000
03
b1 4
02
1&
1*
#225000
1(
1,
#226000
0&
0*
#228000
1(
1,
#229000
b1 1
1&
1*
#231000
0(
0,
#232000
0&
0*
#234000
0(
0,
#235000
1&
1*
#237000
1(
1,
#238000
0&
0*
#240000
1(
1,
#241000
b10 1
1&
1*
#243000
0(
0,
#244000
b0 1
1%
1)
1'
1+
1&
1*
#246000
1(
1,
#247000
0&
0*
#248000
0%
0)
0(
0,
#249000
1(
1,
#250000
b1 1
1&
1*
#252000
1(
1,
#253000
0&
0*
#255000
0(
0,
#256000
1&
1*
#258000
0(
0,
#259000
0&
0*
#261000
1(
1,
#262000
b10 1
1&
1*
#264000
1(
1,
#265000
0&
0*
#267000
0(
0,
#268000
1&
1*
#270000
0(
0,
#271000
0&
0*
#273000
1(
1,
#274000
b11 1
1&
1*
#276000
1(
1,
#277000
0&
0*
#279000
0(
0,
#280000
1&
1*
#282000
0(
0,
#283000
0&
0*
#285000
1(
1,
#286000
b100 1
1&
1*
#288000
1(
1,
#289000
0&
0*
#291000
0(
0,
#292000
1&
1*
#294000
0(
0,
#295000
0&
0*
#297000
1(
1,
#298000
b101 1
1&
1*
#300000
1(
1,
#301000
0&
0*
#303000
0(
0,
#304000
1&
1*
#306000
0(
0,
#307000
0&
0*
#309000
1(
1,
#310000
b110 1
1&
1*
#312000
1(
1,
#313000
0&
0*
#315000
0(
0,
#316000
1&
1*
#318000
0(
0,
#319000
0&
0*
#321000
1(
1,
#322000
b111 1
1&
1*
#324000
1(
1,
#325000
0&
0*
#327000
0(
0,
#328000
1&
1*
#330000
0(
0,
#331000
0&
0*
#333000
1(
1,
#334000
b1000 1
1&
1*
#336000
1(
1,
#337000
0&
0*
#339000
0(
0,
#340000
12
1-
1!
b10 4
1&
1*
#342000
0(
0,
#343000
0&
0*
#345000
1(
1,
#346000
b100 4
13
02
b0 1
1&
1*
#348000
1(
1,
#349000
0&
0*
#351000
0(
0,
#352000
10
1$
b1000 4
1&
1*
#354000
0(
0,
#355000
0&
0*
#357000
1(
1,
#358000
b1 1
1&
1*
#360000
1(
1,
#361000
0&
0*
#363000
0(
0,
#364000
1/
1#
b10000 4
1&
1*
#366000
0(
0,
#367000
0&
0*
#369000
1(
1,
#370000
b10 1
1&
1*
#372000
1(
1,
#373000
0&
0*
#375000
0(
0,
#376000
1&
1*
#378000
0(
0,
#379000
0&
0*
#381000
1(
1,
#382000
b11 1
1&
1*
#384000
1(
1,
#385000
0&
0*
#387000
0(
0,
#388000
1&
1*
#390000
0(
0,
#391000
0&
0*
#393000
1(
1,
#394000
b100 1
1&
1*
#396000
1(
1,
#397000
0&
0*
#399000
0(
0,
#400000
1&
1*
#402000
0(
0,
#403000
0&
0*
#405000
1(
1,
#406000
b101 1
1&
1*
#408000
1(
1,
#409000
0&
0*
#411000
0(
0,
#412000
1&
1*
#414000
0(
0,
#415000
0&
0*
#417000
1(
1,
#418000
b110 1
1&
1*
#420000
1(
1,
#421000
0&
0*
#423000
0(
0,
#424000
1&
1*
#426000
0(
0,
#427000
0&
0*
#429000
1(
1,
#430000
b111 1
1&
1*
#432000
1(
1,
#433000
0&
0*
#435000
0(
0,
#436000
1&
1*
#438000
0(
0,
#439000
0&
0*
#441000
1(
1,
#442000
b1000 1
1&
1*
#444000
1(
1,
#445000
0&
0*
#447000
0(
0,
#448000
12
00
0$
0-
0!
0/
0#
b10000000 4
1&
1*
#450000
1(
1,
#451000
0&
0*
#453000
0(
0,
#454000
03
b1 4
02
b0 1
1&
1*
#456000
1(
1,
#457000
0&
0*
#459000
0(
0,
#460000
1&
1*
#462000
1(
1,
#463000
0&
0*
#465000
0(
0,
#466000
1&
1*
#468000
1(
1,
