fsm_pk.v
module fsm
(
input clk,
input msb_sr,	// most significant bit shift register output
input c_cs,		// conditioned chip select signal put thru input conditioner
input peripheralClkEdge,	// peripheral clockedge of sclk
output reg MISO_BUFF, 			// miso output enable
output reg DM_WE,				// Data Memory Write Enable
output reg ADDR_WE,				// Address Write Enable (for address latch)
output reg SR_WE				// Shift Register Write Enable
);
reg[7:0] state;

localparam GET = 8'b00000001,
		   GOT = 8'b00000010,
		   READ1 = 8'b00000100,
		   READ2 = 8'b00001000,
		   READ3 = 8'b00010000,
		   WRITE1 = 8'b00100000,
		   WRITE2 = 8'b01000000,
		   DONE = 8'b10000000;
reg [3:0] counter;
reg counter_reset;
reg reset_flg;

initial begin
counter = 4'b0000;
counter_reset = 0;
//reset_flg = 0;
end



always @(posedge clk) begin

	//if (counter_reset) begin
	//counter_reset <= 0;
	//counter = 4'b0000;
	//reset_flg <= 1;
	//end

	

	if (peripheralClkEdge && !counter_reset) begin
		counter <= counter + 1;
	end 

	if(counter_reset || c_cs ) begin
		counter <=0;
		counter_reset <= 0;
	end

	if (c_cs) begin
		state <= GET;
		counter <= 4'b0000;
		MISO_BUFF <= 0;
		DM_WE <=0;
		ADDR_WE <=0;
		SR_WE <=0;
	end

	else begin
		case (state)
			GET: begin
				if (counter==4'b1000) begin
					state <= GOT;
				end
				else begin
					state <= GET;
					//counter <= counter + 4'b0001;
				end
			end

			GOT: begin
				if (msb_sr ) begin	// && reset_flg
					state <= READ1;
					//reset_flg <=0;
				end
				else begin
					if (!msb_sr ) begin // && reset_flg
						state <= WRITE1;
						// reset_flg <=0;
					end
				end
			end

			READ1: begin
				state <= READ2;
			end

			READ2: begin
				// reset_flg <= 0;
				state <= READ3;
			end

			READ3: begin
				if (counter == 4'b1000) begin
					state <= DONE;
				end
				else begin
					state <= READ3;
					//counter <= counter + 1;
				end
			end

			WRITE1: begin
				if (counter == 4'b1000) begin
					state <= WRITE2;
					// counter_reset <= 1;
				end
				else begin
					// counter_reset <=0;
					state <= WRITE1;
					//counter <= counter + 1;
				end
			end

			WRITE2: begin
				state <= DONE;
			end

			DONE: begin
				// if (reset_flg); begin
					state <= GET;
					// reset_flg <=0;
				// end
			end
		endcase
//end // @ peripheralclkedge
end
end
always @(state) begin
	case (state)
		GET: begin
			MISO_BUFF <= 0;
			DM_WE <=0;
			ADDR_WE <=0;
			SR_WE <=0;
		end

		GOT: begin
			MISO_BUFF <= 0;
			ADDR_WE <= 1;
			DM_WE <=0;
			SR_WE <=0;
			counter_reset <= 1;
			counter <= 4'b0000;
		end

		READ1: begin
			MISO_BUFF <= 0;
			DM_WE <=0;
			ADDR_WE <=0;
			SR_WE <=0;
		end

		READ2: begin
			MISO_BUFF <= 0;
			DM_WE <=0;
			ADDR_WE <=0;
			SR_WE <=1;
		end

		READ3: begin
			MISO_BUFF <=1;
			DM_WE <=0;
			ADDR_WE <=0;
			SR_WE <=0;
		end

		WRITE1: begin
			MISO_BUFF <= 0;
			DM_WE <=0;
			ADDR_WE <=0;
			SR_WE <=0;
		end

		WRITE2: begin
			MISO_BUFF <= 0;
			DM_WE <=1;
			ADDR_WE <=0;
			SR_WE <=0;
		end

		DONE: begin
			MISO_BUFF <= 0;
			DM_WE <=0;
			ADDR_WE <=0;
			SR_WE <=0;
			counter <= 4'b0000;
		end
	endcase
end // @ state

endmodule

fsm_pk.t.v
//------------------------------------------------------------------------
// Shift Register test bench
//------------------------------------------------------------------------
`timescale 1ns / 1ps

`include "fsm_pk.v"

module testfsm();
    reg clk;
    reg msb_sr;   // most significant bit shift register output
    reg c_cs;     // conditioned chip select signal put thru input conditioner
    reg peripheralClkEdge;    // peripheral clockedge of sclk
//    reg clk;                  // clk
    wire MISO_BUFF;           // miso output enable
    wire DM_WE;               // Data Memory Write Enable
    wire ADDR_WE;             // Address Write Enable (for address latch)
    wire SR_WE;                // Shift Register Write Enable

    // Instantiate with parameter width = 8
    fsm dut( 
    		           .clk(clk),
    		           .msb_sr(msb_sr), 
    		           .c_cs(c_cs), 
                       .peripheralClkEdge(peripheralClkEdge),
    		           .MISO_BUFF(MISO_BUFF), 
    		           .DM_WE(DM_WE),
                       .ADDR_WE(ADDR_WE),
    		           .SR_WE(SR_WE));
    always begin
    #1 clk = ~clk;
   // #2 peripheralClkEdge= ~peripheralClkEdge;
    end

    initial begin
    	// Your Test Code
        $dumpfile("fsm_pk.vcd");
        $dumpvars();

        $display(" clk  |   pclk   |  pload |     pin      |  sin  |      pout     |  sout  |  expected");
        
        // Initial Conditions time = 0
        //clk=1; peripheralClkEdge = 0; msb_sr = 0; c_cs = 1; #2
        // Now we will assign values for different test cases
        clk = 0; peripheralClkEdge = 0; msb_sr = 1; c_cs =1; #4
        peripheralClkEdge = 0; msb_sr = 0; c_cs =0; #2
        peripheralClkEdge = 1; msb_sr = 0; c_cs =0; #2
        peripheralClkEdge = 0; msb_sr = 0; c_cs =0; #2
        peripheralClkEdge = 1; msb_sr = 0; c_cs =0; #2
        peripheralClkEdge = 0; msb_sr = 0; c_cs =0; #2
        peripheralClkEdge = 1; msb_sr = 0; c_cs =0; #2
        peripheralClkEdge = 0; msb_sr = 0; c_cs =0; #2
        peripheralClkEdge = 1; msb_sr = 0; c_cs =0; #2
        peripheralClkEdge = 0; msb_sr = 0; c_cs =0; #2
        peripheralClkEdge = 1; msb_sr = 0; c_cs =0; #2
        peripheralClkEdge = 0; msb_sr = 0; c_cs =0; #2
        peripheralClkEdge = 1; msb_sr = 0; c_cs =0; #2
        peripheralClkEdge = 0; msb_sr = 0; c_cs =0; #2
        peripheralClkEdge = 1; msb_sr = 0; c_cs =0; #2
        peripheralClkEdge = 0; msb_sr = 0; c_cs =0; #2
        peripheralClkEdge = 1; msb_sr = 0; c_cs =0; #2
        peripheralClkEdge = 0; msb_sr = 0; c_cs =0; #2
        peripheralClkEdge = 1; msb_sr = 0; c_cs =0; #2
        peripheralClkEdge = 0; msb_sr = 0; c_cs =0; #2
        peripheralClkEdge = 1; msb_sr = 0; c_cs =0; #2
        peripheralClkEdge = 0; msb_sr = 0; c_cs =0; #2
        peripheralClkEdge = 1; msb_sr = 0; c_cs =0; #2
        peripheralClkEdge = 0; msb_sr = 0; c_cs =0; #2
        peripheralClkEdge = 1; msb_sr = 0; c_cs =0; #2
        peripheralClkEdge = 0; msb_sr = 0; c_cs =0; #2
        peripheralClkEdge = 1; msb_sr = 0; c_cs =0; #2
        peripheralClkEdge = 0; msb_sr = 0; c_cs =0; #2
        peripheralClkEdge = 1; msb_sr = 0; c_cs =0; #2
        peripheralClkEdge = 0; msb_sr = 0; c_cs =0; #2
        peripheralClkEdge = 1; msb_sr = 0; c_cs =0; #2
        peripheralClkEdge = 0; msb_sr = 0; c_cs =0; #2
        peripheralClkEdge = 1; msb_sr = 0; c_cs =0; #2
        peripheralClkEdge = 0; msb_sr = 0; c_cs =0; #2
        peripheralClkEdge = 1; msb_sr = 0; c_cs =0; #2
        peripheralClkEdge = 0; msb_sr = 0; c_cs =0; #2
        peripheralClkEdge = 1; msb_sr = 0; c_cs =0; #2
        peripheralClkEdge = 0; msb_sr = 0; c_cs =0; #2
        peripheralClkEdge = 1; msb_sr = 0; c_cs =0; #2
        peripheralClkEdge = 0; msb_sr = 0; c_cs =0; #2
        peripheralClkEdge = 1; msb_sr = 0; c_cs =0; #2
        peripheralClkEdge = 0; msb_sr = 0; c_cs =0; #2
        peripheralClkEdge = 1; msb_sr = 0; c_cs =0; #2
        peripheralClkEdge = 0; msb_sr = 0; c_cs =0; #2
        peripheralClkEdge = 1; msb_sr = 0; c_cs =0; #2
        peripheralClkEdge = 0; msb_sr = 0; c_cs =0; #2
        peripheralClkEdge = 1; msb_sr = 0; c_cs =0; #2
        peripheralClkEdge = 0; msb_sr = 0; c_cs =0; #2
        peripheralClkEdge = 1; msb_sr = 0; c_cs =0; #2
        peripheralClkEdge = 0; msb_sr = 0; c_cs =0; #2
        peripheralClkEdge = 1; msb_sr = 0; c_cs =0; #2
        peripheralClkEdge = 0; msb_sr = 0; c_cs =0; #2
        peripheralClkEdge = 1; msb_sr = 0; c_cs =0; #2
        peripheralClkEdge = 0; msb_sr = 0; c_cs =0; #2
        peripheralClkEdge = 1; msb_sr = 0; c_cs =0; #2
        peripheralClkEdge = 0; msb_sr = 0; c_cs =0; #2
        peripheralClkEdge = 1; msb_sr = 0; c_cs =0; #2
        peripheralClkEdge = 0; msb_sr = 0; c_cs =0; #2
        peripheralClkEdge = 1; msb_sr = 0; c_cs =0; #2
        peripheralClkEdge = 0; msb_sr = 0; c_cs =0; #2
        peripheralClkEdge = 1; msb_sr = 0; c_cs =0; #2
        peripheralClkEdge = 0; msb_sr = 0; c_cs =0; #2
        peripheralClkEdge = 1; msb_sr = 0; c_cs =0; #2
        peripheralClkEdge = 0; msb_sr = 0; c_cs =0; #2
        peripheralClkEdge = 1; msb_sr = 0; c_cs =0; #2
        peripheralClkEdge = 0; msb_sr = 0; c_cs =0; #2
        peripheralClkEdge = 1; msb_sr = 0; c_cs =0; #2
        peripheralClkEdge = 0; msb_sr = 0; c_cs =0; #2
        peripheralClkEdge = 1; msb_sr = 0; c_cs =0; #2
        peripheralClkEdge = 0; msb_sr = 0; c_cs =0; #2
        peripheralClkEdge = 1; msb_sr = 0; c_cs =0; #2
        peripheralClkEdge = 0; msb_sr = 0; c_cs =0; #2
        peripheralClkEdge = 1; msb_sr = 0; c_cs =0; #2
        peripheralClkEdge = 0; msb_sr = 0; c_cs =0; #2
        peripheralClkEdge = 1; msb_sr = 0; c_cs =0; #2
        peripheralClkEdge = 0; msb_sr = 0; c_cs =0; #2
        peripheralClkEdge = 1; msb_sr = 0; c_cs =0; #2
        peripheralClkEdge = 0; msb_sr = 0; c_cs =0; #2
        peripheralClkEdge = 1; msb_sr = 0; c_cs =0; #2
        peripheralClkEdge = 0; msb_sr = 0; c_cs =0; #2
        peripheralClkEdge = 1; msb_sr = 0; c_cs =0; #2
        peripheralClkEdge = 0; msb_sr = 0; c_cs =0; #2
        peripheralClkEdge = 1; msb_sr = 0; c_cs =0; #2
        peripheralClkEdge = 0; msb_sr = 0; c_cs =0; #2
        peripheralClkEdge = 1; msb_sr = 0; c_cs =0; #2
        peripheralClkEdge = 0; msb_sr = 0; c_cs =0; #2
        peripheralClkEdge = 1; msb_sr = 0; c_cs =0; #2
        peripheralClkEdge = 0; msb_sr = 0; c_cs =0; #2
        peripheralClkEdge = 1; msb_sr = 0; c_cs =0; #2
        peripheralClkEdge = 0; msb_sr = 0; c_cs =0; #2
        peripheralClkEdge = 1; msb_sr = 0; c_cs =0; #2
        peripheralClkEdge = 0; msb_sr = 0; c_cs =0; #2
        peripheralClkEdge = 1; msb_sr = 0; c_cs =0; #2
        peripheralClkEdge = 0; msb_sr = 0; c_cs =0; #2
        peripheralClkEdge = 1; msb_sr = 0; c_cs =0; #2
        peripheralClkEdge = 0; msb_sr = 0; c_cs =0; #2
        peripheralClkEdge = 1; msb_sr = 0; c_cs =0; #2
        peripheralClkEdge = 0; msb_sr = 0; c_cs =0; #2
        peripheralClkEdge = 1; msb_sr = 0; c_cs =0; #2
        peripheralClkEdge = 0; msb_sr = 0; c_cs =0; #2
        peripheralClkEdge = 1; msb_sr = 0; c_cs =0; #2
        peripheralClkEdge = 0; msb_sr = 0; c_cs =0; #2
        peripheralClkEdge = 1; msb_sr = 0; c_cs =0; #2
        peripheralClkEdge = 0; msb_sr = 0; c_cs =0; #2
        peripheralClkEdge = 1; msb_sr = 0; c_cs =0; #2
        peripheralClkEdge = 0; msb_sr = 0; c_cs =0; #2
        peripheralClkEdge = 1; msb_sr = 0; c_cs =0; #2
        peripheralClkEdge = 0; msb_sr = 0; c_cs =0; #2
        peripheralClkEdge = 1; msb_sr = 0; c_cs =0; #2
        peripheralClkEdge = 0; msb_sr = 0; c_cs =0; #2
        peripheralClkEdge = 1; msb_sr = 0; c_cs =0; #2
        peripheralClkEdge = 0; msb_sr = 0; c_cs =0; #2
        peripheralClkEdge = 1; msb_sr = 0; c_cs =0; #2
        peripheralClkEdge = 0; msb_sr = 0; c_cs =0; #2
        peripheralClkEdge = 1; msb_sr = 0; c_cs =0; #2
        peripheralClkEdge = 0; msb_sr = 0; c_cs =0; #2
        peripheralClkEdge = 1; msb_sr = 0; c_cs =0; #2
        peripheralClkEdge = 0; msb_sr = 0; c_cs =0; #2
        peripheralClkEdge = 1; msb_sr = 0; c_cs =0; #2
        peripheralClkEdge = 0; msb_sr = 0; c_cs =0; #2
        peripheralClkEdge = 1; msb_sr = 0; c_cs =0; #2
        

        peripheralClkEdge = 0; msb_sr = 1; c_cs =1; #2
        peripheralClkEdge = 1; msb_sr = 1; c_cs =1; #2
        peripheralClkEdge = 0; msb_sr = 1; c_cs =1; #2
        peripheralClkEdge = 1; msb_sr = 1; c_cs =1; #2
        peripheralClkEdge = 0; msb_sr = 1; c_cs =0; #2
        peripheralClkEdge = 1; msb_sr = 1; c_cs =0; #2
        peripheralClkEdge = 0; msb_sr = 1; c_cs =0; #2
        peripheralClkEdge = 1; msb_sr = 1; c_cs =0; #2
        peripheralClkEdge = 0; msb_sr = 1; c_cs =0; #2
        peripheralClkEdge = 1; msb_sr = 1; c_cs =0; #2
        peripheralClkEdge = 0; msb_sr = 1; c_cs =0; #2
        peripheralClkEdge = 1; msb_sr = 1; c_cs =0; #2
        peripheralClkEdge = 0; msb_sr = 1; c_cs =0; #2
        peripheralClkEdge = 1; msb_sr = 1; c_cs =0; #2
        peripheralClkEdge = 0; msb_sr = 1; c_cs =0; #2
        peripheralClkEdge = 1; msb_sr = 1; c_cs =0; #2
        peripheralClkEdge = 0; msb_sr = 1; c_cs =0; #2
        peripheralClkEdge = 1; msb_sr = 1; c_cs =0; #2
        peripheralClkEdge = 0; msb_sr = 1; c_cs =0; #2
        peripheralClkEdge = 1; msb_sr = 1; c_cs =0; #2
        peripheralClkEdge = 0; msb_sr = 1; c_cs =0; #2
        peripheralClkEdge = 1; msb_sr = 1; c_cs =0; #2
        peripheralClkEdge = 0; msb_sr = 1; c_cs =0; #2
        peripheralClkEdge = 1; msb_sr = 1; c_cs =0; #2
        peripheralClkEdge = 0; msb_sr = 1; c_cs =0; #2
        peripheralClkEdge = 1; msb_sr = 1; c_cs =0; #2
        peripheralClkEdge = 0; msb_sr = 1; c_cs =0; #2
        peripheralClkEdge = 1; msb_sr = 1; c_cs =0; #2
        peripheralClkEdge = 0; msb_sr = 1; c_cs =0; #2
        peripheralClkEdge = 1; msb_sr = 1; c_cs =0; #2
        peripheralClkEdge = 0; msb_sr = 1; c_cs =0; #2
        peripheralClkEdge = 1; msb_sr = 1; c_cs =0; #2
        peripheralClkEdge = 0; msb_sr = 1; c_cs =0; #2
        peripheralClkEdge = 1; msb_sr = 1; c_cs =0; #2
        peripheralClkEdge = 0; msb_sr = 1; c_cs =0; #2
        peripheralClkEdge = 1; msb_sr = 1; c_cs =0; #2
        peripheralClkEdge = 0; msb_sr = 1; c_cs =0; #2
        peripheralClkEdge = 1; msb_sr = 1; c_cs =0; #2
        peripheralClkEdge = 0; msb_sr = 1; c_cs =0; #2
        peripheralClkEdge = 1; msb_sr = 1; c_cs =0; #2
        peripheralClkEdge = 0; msb_sr = 1; c_cs =0; #2
        peripheralClkEdge = 1; msb_sr = 1; c_cs =0; #2
        peripheralClkEdge = 0; msb_sr = 1; c_cs =0; #2
        peripheralClkEdge = 1; msb_sr = 1; c_cs =0; #2
        peripheralClkEdge = 0; msb_sr = 1; c_cs =0; #2
        peripheralClkEdge = 1; msb_sr = 1; c_cs =0; #2
        peripheralClkEdge = 0; msb_sr = 1; c_cs =0; #2
        peripheralClkEdge = 1; msb_sr = 1; c_cs =0; #2
        peripheralClkEdge = 0; msb_sr = 1; c_cs =0; #2
        peripheralClkEdge = 1; msb_sr = 1; c_cs =0; #2
        peripheralClkEdge = 0; msb_sr = 1; c_cs =0; #2
        peripheralClkEdge = 1; msb_sr = 1; c_cs =0; #2
        peripheralClkEdge = 0; msb_sr = 1; c_cs =0; #2
        peripheralClkEdge = 1; msb_sr = 1; c_cs =0; #2
        peripheralClkEdge = 0; msb_sr = 1; c_cs =0; #2
        peripheralClkEdge = 1; msb_sr = 1; c_cs =0; #2
        peripheralClkEdge = 0; msb_sr = 1; c_cs =0; #2
        peripheralClkEdge = 1; msb_sr = 1; c_cs =0; #2
        peripheralClkEdge = 0; msb_sr = 1; c_cs =0; #2
        peripheralClkEdge = 1; msb_sr = 1; c_cs =0; #2
        peripheralClkEdge = 0; msb_sr = 1; c_cs =0; #2
        peripheralClkEdge = 1; msb_sr = 1; c_cs =0; #2
        peripheralClkEdge = 0; msb_sr = 1; c_cs =0; #2
        peripheralClkEdge = 1; msb_sr = 1; c_cs =0; #2
        peripheralClkEdge = 0; msb_sr = 1; c_cs =0; #2
        peripheralClkEdge = 1; msb_sr = 1; c_cs =0; #2
        peripheralClkEdge = 0; msb_sr = 1; c_cs =0; #2
        peripheralClkEdge = 1; msb_sr = 1; c_cs =0; #2
        peripheralClkEdge = 0; msb_sr = 1; c_cs =0; #2
        peripheralClkEdge = 1; msb_sr = 1; c_cs =0; #2
        peripheralClkEdge = 0; msb_sr = 1; c_cs =0; #2
        peripheralClkEdge = 1; msb_sr = 1; c_cs =0; #2
        peripheralClkEdge = 0; msb_sr = 1; c_cs =0; #2
        peripheralClkEdge = 1; msb_sr = 1; c_cs =0; #2
        peripheralClkEdge = 0; msb_sr = 1; c_cs =0; #2
        peripheralClkEdge = 1; msb_sr = 1; c_cs =0; #2
        peripheralClkEdge = 0; msb_sr = 1; c_cs =0; #2
        peripheralClkEdge = 1; msb_sr = 1; c_cs =0; #2
        peripheralClkEdge = 0; msb_sr = 1; c_cs =0; #2
        peripheralClkEdge = 1; msb_sr = 1; c_cs =0; #2
        peripheralClkEdge = 0; msb_sr = 1; c_cs =0; #2
        peripheralClkEdge = 1; msb_sr = 1; c_cs =0; #2
        peripheralClkEdge = 0; msb_sr = 1; c_cs =0; #2
        peripheralClkEdge = 1; msb_sr = 1; c_cs =0; #2
        peripheralClkEdge = 0; msb_sr = 1; c_cs =0; #2
        peripheralClkEdge = 1; msb_sr = 1; c_cs =0; #2
        peripheralClkEdge = 0; msb_sr = 1; c_cs =0; #2
        peripheralClkEdge = 1; msb_sr = 1; c_cs =0; #2
        peripheralClkEdge = 0; msb_sr = 1; c_cs =0; #2
        peripheralClkEdge = 1; msb_sr = 1; c_cs =0; #2
        peripheralClkEdge = 0; msb_sr = 1; c_cs =0; #2
        peripheralClkEdge = 1; msb_sr = 1; c_cs =0; #2
        peripheralClkEdge = 0; msb_sr = 1; c_cs =0; #2
        peripheralClkEdge = 1; msb_sr = 1; c_cs =0; #2
        peripheralClkEdge = 0; msb_sr = 1; c_cs =0; #2
        peripheralClkEdge = 1; msb_sr = 1; c_cs =0; #2
        peripheralClkEdge = 0; msb_sr = 1; c_cs =0; #2
        peripheralClkEdge = 1; msb_sr = 1; c_cs =0; #2
        peripheralClkEdge = 0; msb_sr = 1; c_cs =0; #2        
        peripheralClkEdge = 1; msb_sr = 1; c_cs =0; #2
        peripheralClkEdge = 0; msb_sr = 1; c_cs =0; #2
        peripheralClkEdge = 1; msb_sr = 1; c_cs =0; #2
        peripheralClkEdge = 0; msb_sr = 1; c_cs =0; #2
        peripheralClkEdge = 1; msb_sr = 1; c_cs =0; #2
        peripheralClkEdge = 0; msb_sr = 1; c_cs =0; #2
        peripheralClkEdge = 1; msb_sr = 1; c_cs =0; #2
        peripheralClkEdge = 0; msb_sr = 1; c_cs =0; #2
        peripheralClkEdge = 1; msb_sr = 1; c_cs =0; #2
        peripheralClkEdge = 0; msb_sr = 1; c_cs =0; #2
        peripheralClkEdge = 1; msb_sr = 1; c_cs =0; #2
        peripheralClkEdge = 0; msb_sr = 1; c_cs =0; #2
        peripheralClkEdge = 1; msb_sr = 1; c_cs =0; #2
        peripheralClkEdge = 0; msb_sr = 1; c_cs =0; #2

        #20 $finish;
    end

endmodule

fsm_pk.vcd
$date
	Wed Oct 26 01:08:54 2016
$end
$version
	Icarus Verilog
$end
$timescale
	1ps
$end
$scope module testfsm $end
$var wire 1 ! ADDR_WE $end
$var wire 1 " DM_WE $end
$var wire 1 # MISO_BUFF $end
$var wire 1 $ SR_WE $end
$var reg 1 % c_cs $end
$var reg 1 & clk $end
$var reg 1 ' msb_sr $end
$var reg 1 ( peripheralClkEdge $end
$scope module dut $end
$var wire 1 ) c_cs $end
$var wire 1 * clk $end
$var wire 1 + msb_sr $end
$var wire 1 , peripheralClkEdge $end
$var reg 1 - ADDR_WE $end
$var reg 1 . DM_WE $end
$var reg 1 / MISO_BUFF $end
$var reg 1 0 SR_WE $end
$var reg 4 1 counter [3:0] $end
$var reg 1 2 counter_reset $end
$var reg 1 3 reset_flg $end
$var reg 8 4 state [7:0] $end
$upscope $end
$upscope $end
$enddefinitions $end
#0
$dumpvars
bx 4
03
02
b0 1
x0
x/
x.
x-
0,
1+
0*
1)
0(
1'
0&
1%
x$
x#
x"
x!
$end
#1000
00
0$
0-
0!
0.
0"
0/
0#
b1 4
1&
1*
#2000
0&
0*
#3000
1&
1*
#4000
0&
0*
0%
0)
0'
0+
#5000
1&
1*
#6000
0&
0*
1(
1,
#7000
b1 1
1&
1*
#8000
0&
0*
0(
0,
#9000
1&
1*
#10000
0&
0*
1(
1,
#11000
b10 1
1&
1*
#12000
0&
0*
0(
0,
#13000
1&
1*
#14000
0&
0*
1(
1,
#15000
b11 1
1&
1*
#16000
0&
0*
0(
0,
#17000
1&
1*
#18000
0&
0*
1(
1,
#19000
b100 1
1&
1*
#20000
0&
0*
0(
0,
#21000
1&
1*
#22000
0&
0*
1(
1,
#23000
b101 1
1&
1*
#24000
0&
0*
0(
0,
#25000
1&
1*
#26000
0&
0*
1(
1,
#27000
b110 1
1&
1*
#28000
0&
0*
0(
0,
#29000
1&
1*
#30000
0&
0*
1(
1,
#31000
b111 1
1&
1*
#32000
0&
0*
0(
0,
#33000
1&
1*
#34000
0&
0*
1(
1,
#35000
b1000 1
1&
1*
#36000
0&
0*
0(
0,
#37000
12
1-
1!
b10 4
1&
1*
#38000
0&
0*
1(
1,
#39000
0-
0!
b100000 4
02
b0 1
1&
1*
#40000
0&
0*
0(
0,
#41000
1&
1*
#42000
0&
0*
1(
1,
#43000
b1 1
1&
1*
#44000
0&
0*
0(
0,
#45000
1&
1*
#46000
0&
0*
1(
1,
#47000
b10 1
1&
1*
#48000
0&
0*
0(
0,
#49000
1&
1*
#50000
0&
0*
1(
1,
#51000
b11 1
1&
1*
#52000
0&
0*
0(
0,
#53000
1&
1*
#54000
0&
0*
1(
1,
#55000
b100 1
1&
1*
#56000
0&
0*
0(
0,
#57000
1&
1*
#58000
0&
0*
1(
1,
#59000
b101 1
1&
1*
#60000
0&
0*
0(
0,
#61000
1&
1*
#62000
0&
0*
1(
1,
#63000
b110 1
1&
1*
#64000
0&
0*
0(
0,
#65000
1&
1*
#66000
0&
0*
1(
1,
#67000
b111 1
1&
1*
#68000
0&
0*
0(
0,
#69000
1&
1*
#70000
0&
0*
1(
1,
#71000
b1000 1
1&
1*
#72000
0&
0*
0(
0,
#73000
1.
1"
b1000000 4
1&
1*
#74000
0&
0*
1(
1,
#75000
0.
0"
b10000000 4
b0 1
1&
1*
#76000
0&
0*
0(
0,
#77000
b1 4
1&
1*
#78000
0&
0*
1(
1,
#79000
b1 1
1&
1*
#80000
0&
0*
0(
0,
#81000
1&
1*
#82000
0&
0*
1(
1,
#83000
b10 1
1&
1*
#84000
0&
0*
0(
0,
#85000
1&
1*
#86000
0&
0*
1(
1,
#87000
b11 1
1&
1*
#88000
0&
0*
0(
0,
#89000
1&
1*
#90000
0&
0*
1(
1,
#91000
b100 1
1&
1*
#92000
0&
0*
0(
0,
#93000
1&
1*
#94000
0&
0*
1(
1,
#95000
b101 1
1&
1*
#96000
0&
0*
0(
0,
#97000
1&
1*
#98000
0&
0*
1(
1,
#99000
b110 1
1&
1*
#100000
0&
0*
0(
0,
#101000
1&
1*
#102000
0&
0*
1(
1,
#103000
b111 1
1&
1*
#104000
0&
0*
0(
0,
#105000
1&
1*
#106000
0&
0*
1(
1,
#107000
b1000 1
1&
1*
#108000
0&
0*
0(
0,
#109000
12
1-
1!
b10 4
1&
1*
#110000
0&
0*
1(
1,
#111000
0-
0!
b100000 4
02
b0 1
1&
1*
#112000
0&
0*
0(
0,
#113000
1&
1*
#114000
0&
0*
1(
1,
#115000
b1 1
1&
1*
#116000
0&
0*
0(
0,
#117000
1&
1*
#118000
0&
0*
1(
1,
#119000
b10 1
1&
1*
#120000
0&
0*
0(
0,
#121000
1&
1*
#122000
0&
0*
1(
1,
#123000
b11 1
1&
1*
#124000
0&
0*
0(
0,
#125000
1&
1*
#126000
0&
0*
1(
1,
#127000
b100 1
1&
1*
#128000
0&
0*
0(
0,
#129000
1&
1*
#130000
0&
0*
1(
1,
#131000
b101 1
1&
1*
#132000
0&
0*
0(
0,
#133000
1&
1*
#134000
0&
0*
1(
1,
#135000
b110 1
1&
1*
#136000
0&
0*
0(
0,
#137000
1&
1*
#138000
0&
0*
1(
1,
#139000
b111 1
1&
1*
#140000
0&
0*
0(
0,
#141000
1&
1*
#142000
0&
0*
1(
1,
#143000
b1000 1
1&
1*
#144000
0&
0*
0(
0,
#145000
1.
1"
b1000000 4
1&
1*
#146000
0&
0*
1(
1,
#147000
0.
0"
b10000000 4
b0 1
1&
1*
#148000
0&
0*
0(
0,
#149000
b1 4
1&
1*
#150000
0&
0*
1(
1,
#151000
b1 1
1&
1*
#152000
0&
0*
0(
0,
#153000
1&
1*
#154000
0&
0*
1(
1,
#155000
b10 1
1&
1*
#156000
0&
0*
0(
0,
#157000
1&
1*
#158000
0&
0*
1(
1,
#159000
b11 1
1&
1*
#160000
0&
0*
0(
0,
#161000
1&
1*
#162000
0&
0*
1(
1,
#163000
b100 1
1&
1*
#164000
0&
0*
0(
0,
#165000
1&
1*
#166000
0&
0*
1(
1,
#167000
b101 1
1&
1*
#168000
0&
0*
0(
0,
#169000
1&
1*
#170000
0&
0*
1(
1,
#171000
b110 1
1&
1*
#172000
0&
0*
0(
0,
#173000
1&
1*
#174000
0&
0*
1(
1,
#175000
b111 1
1&
1*
#176000
0&
0*
0(
0,
#177000
1&
1*
#178000
0&
0*
1(
1,
#179000
b1000 1
1&
1*
#180000
0&
0*
0(
0,
#181000
12
1-
1!
b10 4
1&
1*
#182000
0&
0*
1(
1,
#183000
0-
0!
b100000 4
02
b0 1
1&
1*
#184000
0&
0*
0(
0,
#185000
1&
1*
#186000
0&
0*
1(
1,
#187000
b1 1
1&
1*
#188000
0&
0*
0(
0,
#189000
1&
1*
#190000
0&
0*
1(
1,
#191000
b10 1
1&
1*
#192000
0&
0*
0(
0,
#193000
1&
1*
#194000
0&
0*
1(
1,
#195000
b11 1
1&
1*
#196000
0&
0*
0(
0,
#197000
1&
1*
#198000
0&
0*
1(
1,
#199000
b100 1
1&
1*
#200000
0&
0*
0(
0,
#201000
1&
1*
#202000
0&
0*
1(
1,
#203000
b101 1
1&
1*
#204000
0&
0*
0(
0,
#205000
1&
1*
#206000
0&
0*
1(
1,
#207000
b110 1
1&
1*
#208000
0&
0*
0(
0,
#209000
1&
1*
#210000
0&
0*
1(
1,
#211000
b111 1
1&
1*
#212000
0&
0*
0(
0,
#213000
1&
1*
#214000
0&
0*
1(
1,
#215000
b1000 1
1&
1*
#216000
0&
0*
0(
0,
#217000
1.
1"
b1000000 4
1&
1*
#218000
0&
0*
1(
1,
#219000
0.
0"
b10000000 4
b0 1
1&
1*
#220000
0&
0*
0(
0,
#221000
b1 4
1&
1*
#222000
0&
0*
1(
1,
#223000
b1 1
1&
1*
#224000
0&
0*
0(
0,
#225000
1&
1*
#226000
0&
0*
1(
1,
#227000
b10 1
1&
1*
#228000
0&
0*
0(
0,
#229000
1&
1*
#230000
0&
0*
1(
1,
#231000
b11 1
1&
1*
#232000
0&
0*
0(
0,
#233000
1&
1*
#234000
0&
0*
1(
1,
#235000
b100 1
1&
1*
#236000
0&
0*
0(
0,
#237000
1&
1*
#238000
0&
0*
1(
1,
#239000
b101 1
1&
1*
#240000
0&
0*
0(
0,
#241000
1&
1*
#242000
0&
0*
1(
1,
#243000
b110 1
1&
1*
#244000
0&
0*
1%
1)
1'
1+
0(
0,
#245000
b0 1
1&
1*
#246000
0&
0*
1(
1,
#247000
b0 1
1&
1*
#248000
0&
0*
0(
0,
#249000
1&
1*
#250000
0&
0*
1(
1,
#251000
b0 1
1&
1*
#252000
0&
0*
0%
0)
0(
0,
#253000
1&
1*
#254000
0&
0*
1(
1,
#255000
b1 1
1&
1*
#256000
0&
0*
0(
0,
#257000
1&
1*
#258000
0&
0*
1(
1,
#259000
b10 1
1&
1*
#260000
0&
0*
0(
0,
#261000
1&
1*
#262000
0&
0*
1(
1,
#263000
b11 1
1&
1*
#264000
0&
0*
0(
0,
#265000
1&
1*
#266000
0&
0*
1(
1,
#267000
b100 1
1&
1*
#268000
0&
0*
0(
0,
#269000
1&
1*
#270000
0&
0*
1(
1,
#271000
b101 1
1&
1*
#272000
0&
0*
0(
0,
#273000
1&
1*
#274000
0&
0*
1(
1,
#275000
b110 1
1&
1*
#276000
0&
0*
0(
0,
#277000
1&
1*
#278000
0&
0*
1(
1,
#279000
b111 1
1&
1*
#280000
0&
0*
0(
0,
#281000
1&
1*
#282000
0&
0*
1(
1,
#283000
b1000 1
1&
1*
#284000
0&
0*
0(
0,
#285000
12
1-
1!
b10 4
1&
1*
#286000
0&
0*
1(
1,
#287000
0-
0!
b100 4
02
b0 1
1&
1*
#288000
0&
0*
0(
0,
#289000
10
1$
b1000 4
1&
1*
