shiftregister.v
//------------------------------------------------------------------------
// Shift Register
//   Parameterized width (in bits)
//   Shift register can operate in two modes:
//      - serial in, parallel out
//      - parallel in, serial out
//------------------------------------------------------------------------

module shiftregister
#(parameter width = 8)
(
input               clk,                // FPGA Clock
input               peripheralClkEdge,  // Edge indicator
input               parallelLoad,       // 1 = Load shift reg with parallelDataIn
input  [width-1:0]  parallelDataIn,     // Load shift reg in parallel
input               serialDataIn,       // Load shift reg serially
output [width-1:0]  parallelDataOut,    // Shift reg data contents
output              serialDataOut       // Positive edge synchronized
);

    reg [width-1:0]      shiftregistermem;
    always @(posedge clk) begin
        // Your Code Here
        if (parallelLoad) begin
        	shiftregistermem <= parallelDataIn;
        end
        else @(posedge peripheralClkEdge) begin
        	shiftregistermem <= shiftregistermem << 1;
        	shiftregistermem[0] <= serialDataIn;
        end
    end
    assign parallelDataOut = shiftregistermem;
    assign serialDataOut = shiftregistermem[width-1];

endmodule

shiftregister.t.v
//------------------------------------------------------------------------
// Shift Register test bench
//------------------------------------------------------------------------
`timescale 1ns / 1ps

`include "shiftregister.v"

module testshiftregister();

    reg             clk;
    reg             peripheralClkEdge;
    reg             parallelLoad;
    wire[7:0]       parallelDataOut;
    wire            serialDataOut;
    reg[7:0]        parallelDataIn;
    reg             serialDataIn; 
    
    // Instantiate with parameter width = 8
    shiftregister #(8) dut(.clk(clk), 
    		           .peripheralClkEdge(peripheralClkEdge),
    		           .parallelLoad(parallelLoad), 
    		           .parallelDataIn(parallelDataIn), 
    		           .serialDataIn(serialDataIn), 
    		           .parallelDataOut(parallelDataOut), 
    		           .serialDataOut(serialDataOut));
    always begin
    #1 clk = ~clk;
    //#6 peripheralClkEdge= ~peripheralClkEdge;
    end

    initial begin
    	// Your Test Code
        $dumpfile("shiftregister.vcd");
        $dumpvars();

        $display(" clk  |   pclk   |  pload |     pin      |  sin  |      pout     |  sout  |  expected");
        
        clk=1; 
        
        peripheralClkEdge=0;
        parallelLoad=0; parallelDataIn=8'b00000000; serialDataIn=1;#10
        $display("  %b  |    %b     |    %b   |   %b   |   %b   |   %b    |   %b    |  00000000   0",  1, 1'b0, parallelLoad, parallelDataIn, serialDataIn, parallelDataOut, serialDataOut);
        
        parallelLoad=1;#10
        $display("  %b  |    %b     |    %b   |   %b   |   %b   |   %b    |   %b    |  00000000   0",  1, 1'b0, parallelLoad, parallelDataIn, serialDataIn, parallelDataOut, serialDataOut); 

        parallelLoad=0; serialDataIn=1;#8
        peripheralClkEdge = 1; #10
        $display("  %b  |    %b     |    %b   |   %b   |   %b   |   %b    |   %b    |  00000001   0",  1, 1'b1, parallelLoad, parallelDataIn, serialDataIn, parallelDataOut, serialDataOut);
        
        peripheralClkEdge = 0; #10
        parallelLoad=0; parallelDataIn=8'b11110000; serialDataIn=1; #10 
        peripheralClkEdge = 1; #10
        $display("  %b  |    %b     |    %b   |   %b   |   %b   |   %b    |   %b    |  11100001   1",  1, 1'b0, parallelLoad, parallelDataIn, serialDataIn, parallelDataOut, serialDataOut);
        
        parallelLoad=1; parallelDataIn=8'b11110000; serialDataIn=1; #10 
        $display("  %b  |    %b     |    %b   |   %b   |   %b   |   %b    |   %b    |  11100001   1",  1, 1'b0, parallelLoad, parallelDataIn, serialDataIn, parallelDataOut, serialDataOut);
        
        parallelLoad=1; parallelDataIn=8'b11110000; serialDataIn=1;
        $display("  %b  |    %b     |    %b   |   %b   |   %b   |   %b    |   %b    |  11100001   1",  1, 1'b1, parallelLoad, parallelDataIn, serialDataIn, parallelDataOut, serialDataOut);


        #60 $finish;
    end

endmodule

shiftregister.vcd
$date
	Tue Oct 18 04:03:39 2016
$end
$version
	Icarus Verilog
$end
$timescale
	1ps
$end
$scope module testshiftregister $end
$var wire 8 ! parallelDataOut [7:0] $end
$var wire 1 " serialDataOut $end
$var reg 1 # clk $end
$var reg 8 $ parallelDataIn [7:0] $end
$var reg 1 % parallelLoad $end
$var reg 1 & peripheralClkEdge $end
$var reg 1 ' serialDataIn $end
$scope module dut $end
$var wire 1 ( clk $end
$var wire 8 ) parallelDataIn [7:0] $end
$var wire 8 * parallelDataOut [7:0] $end
$var wire 1 + parallelLoad $end
$var wire 1 , peripheralClkEdge $end
$var wire 1 - serialDataIn $end
$var wire 1 " serialDataOut $end
$var reg 8 . shiftregistermem [7:0] $end
$upscope $end
$upscope $end
$enddefinitions $end
#0
$dumpvars
bx .
1-
0,
0+
bx *
b0 )
1(
1'
0&
0%
b0 $
1#
x"
bx !
$end
#1000
0#
0(
#2000
1#
1(
#3000
0#
0(
#4000
1#
1(
#5000
0#
0(
#6000
1#
1(
#7000
0#
0(
#8000
1#
1(
#9000
0#
0(
#10000
1#
1(
1%
1+
#11000
0#
0(
#12000
1#
1(
#13000
0#
0(
#14000
1#
1(
#15000
0#
0(
#16000
1#
1(
#17000
0#
0(
#18000
1#
1(
#19000
0#
0(
#20000
1#
1(
0%
0+
#21000
0#
0(
#22000
1#
1(
#23000
0#
0(
#24000
1#
1(
#25000
0#
0(
#26000
1#
1(
#27000
0#
0(
#28000
bx1 .
bx1 !
bx1 *
1#
1(
1&
1,
#29000
0#
0(
#30000
1#
1(
#31000
0#
0(
#32000
1#
1(
#33000
0#
0(
#34000
1#
1(
#35000
0#
0(
#36000
1#
1(
#37000
0#
0(
#38000
1#
1(
0&
0,
#39000
0#
0(
#40000
1#
1(
#41000
0#
0(
#42000
1#
1(
#43000
0#
0(
#44000
1#
1(
#45000
0#
0(
#46000
1#
1(
#47000
0#
0(
#48000
1#
1(
b11110000 $
b11110000 )
#49000
0#
0(
#50000
1#
1(
#51000
0#
0(
#52000
1#
1(
#53000
0#
0(
#54000
1#
1(
#55000
0#
0(
#56000
1#
1(
#57000
0#
0(
#58000
bx11 .
bx11 !
bx11 *
1#
1(
1&
1,
#59000
0#
0(
#60000
1#
1(
#61000
0#
0(
#62000
1#
1(
#63000
0#
0(
#64000
1#
1(
#65000
0#
0(
#66000
1#
1(
#67000
0#
0(
#68000
1#
1(
1%
1+
